{
  "videoId": "nvSKMcS7Bdk",
  "musicId": "A0014",
  "times": [
    { "id": 9801, "time": 31 },
    { "id": 1, "time": 34.94 },
    { "id": 2, "time": 43.55 },
    { "id": 3, "time": 53.17 },
    { "id": 4, "time": 60.55 },
    { "id": 5, "time": 68.33 },
    { "id": 6, "time": 75.82 },
    { "id": 7, "time": 83.62 },
    { "id": 8, "time": 91.15 },
    { "id": 9, "time": 99.1 },
    { "id": 10, "time": 106.59 },
    { "id": 11, "time": 113.65 },
    { "id": 12, "time": 120.78 },
    { "id": 13, "time": 127.97 },
    { "id": 14, "time": 135.63 },
    { "id": 15, "time": 143.75 },
    { "id": 16, "time": 151.77 },
    { "id": 17, "time": 159.04 },
    { "id": 18, "time": 160.4 },
    { "id": 19, "time": 161.44 },
    { "id": 20, "time": 162.49 },
    { "id": 21, "time": 163.49 },
    { "id": 22, "time": 164.51 },
    { "id": 23, "time": 165.5 },
    { "id": 24, "time": 166.53 },
    { "id": 25, "time": 167.49 },
    { "id": 26, "time": 168.62 },
    { "id": 27, "time": 169.7 },
    { "id": 28, "time": 170.73 },
    { "id": 29, "time": 171.7 },
    { "id": 30, "time": 172.74 },
    { "id": 31, "time": 173.73 },
    { "id": 32, "time": 174.8 },
    { "id": 33, "time": 175.87 },
    { "id": 34, "time": 176.91 },
    { "id": 35, "time": 177.92 },
    { "id": 36, "time": 178.87 },
    { "id": 37, "time": 179.92 },
    { "id": 38, "time": 180.92 },
    { "id": 39, "time": 181.93 },
    { "id": 40, "time": 182.93 },
    { "id": 41, "time": 183.94 },
    { "id": 42, "time": 184.88 },
    { "id": 43, "time": 185.89 },
    { "id": 44, "time": 186.87 },
    { "id": 45, "time": 187.85 },
    { "id": 46, "time": 188.82 },
    { "id": 47, "time": 189.81 },
    { "id": 48, "time": 190.74 },
    { "id": 49, "time": 191.74 },
    { "id": 50, "time": 192.71 },
    { "id": 51, "time": 193.69 },
    { "id": 52, "time": 194.66 },
    { "id": 53, "time": 195.63 },
    { "id": 54, "time": 196.62 },
    { "id": 55, "time": 197.6 },
    { "id": 56, "time": 198.63 },
    { "id": 57, "time": 199.6 },
    { "id": 58, "time": 200.52 },
    { "id": 59, "time": 201.48 },
    { "id": 60, "time": 202.5 },
    { "id": 61, "time": 203.49 },
    { "id": 62, "time": 204.49 },
    { "id": 63, "time": 205.38 },
    { "id": 64, "time": 206.41 },
    { "id": 65, "time": 207.4 },
    { "id": 66, "time": 208.5 },
    { "id": 67, "time": 209.57 },
    { "id": 68, "time": 210.62 },
    { "id": 69, "time": 211.55 },
    { "id": 70, "time": 212.57 },
    { "id": 71, "time": 213.62 },
    { "id": 72, "time": 214.65 },
    { "id": 73, "time": 215.62 },
    { "id": 74, "time": 216.7 },
    { "id": 75, "time": 217.72 },
    { "id": 76, "time": 218.66 },
    { "id": 77, "time": 219.65 },
    { "id": 78, "time": 220.68 },
    { "id": 79, "time": 221.7 },
    { "id": 80, "time": 222.69 },
    { "id": 81, "time": 223.72 },
    { "id": 82, "time": 224.71 },
    { "id": 83, "time": 225.72 },
    { "id": 84, "time": 226.71 },
    { "id": 85, "time": 227.73 },
    { "id": 86, "time": 228.7 },
    { "id": 87, "time": 229.69 },
    { "id": 88, "time": 230.7 },
    { "id": 89, "time": 231.67 },
    { "id": 90, "time": 232.62 },
    { "id": 91, "time": 233.64 },
    { "id": 92, "time": 234.65 },
    { "id": 93, "time": 235.6 },
    { "id": 94, "time": 236.61 },
    { "id": 95, "time": 237.62 },
    { "id": 96, "time": 238.61 },
    { "id": 97, "time": 239.61 },
    { "id": 98, "time": 240.57 },
    { "id": 99, "time": 241.61 },
    { "id": 100, "time": 242.64 },
    { "id": 101, "time": 243.61 },
    { "id": 102, "time": 244.64 },
    { "id": 103, "time": 245.63 },
    { "id": 104, "time": 246.64 },
    { "id": 105, "time": 247.64 },
    { "id": 106, "time": 248.69 },
    { "id": 107, "time": 249.68 },
    { "id": 108, "time": 250.72 },
    { "id": 109, "time": 251.74 },
    { "id": 110, "time": 252.8 },
    { "id": 111, "time": 253.72 },
    { "id": 112, "time": 254.72 },
    { "id": 113, "time": 255.7 },
    { "id": 114, "time": 256.74 },
    { "id": 115, "time": 257.72 },
    { "id": 116, "time": 258.7 },
    { "id": 117, "time": 259.73 },
    { "id": 118, "time": 260.68 },
    { "id": 119, "time": 261.65 },
    { "id": 120, "time": 262.69 },
    { "id": 121, "time": 263.69 },
    { "id": 122, "time": 264.64 },
    { "id": 123, "time": 265.64 },
    { "id": 124, "time": 266.64 },
    { "id": 18, "time": 267.68 },
    { "id": 19, "time": 268.74 },
    { "id": 20, "time": 269.81 },
    { "id": 21, "time": 270.72 },
    { "id": 22, "time": 271.71 },
    { "id": 23, "time": 272.74 },
    { "id": 24, "time": 273.72 },
    { "id": 25, "time": 274.72 },
    { "id": 26, "time": 275.77 },
    { "id": 27, "time": 276.86 },
    { "id": 28, "time": 277.86 },
    { "id": 29, "time": 278.83 },
    { "id": 30, "time": 279.83 },
    { "id": 31, "time": 280.82 },
    { "id": 32, "time": 281.85 },
    { "id": 33, "time": 282.89 },
    { "id": 34, "time": 283.91 },
    { "id": 35, "time": 284.93 },
    { "id": 36, "time": 285.92 },
    { "id": 37, "time": 286.89 },
    { "id": 38, "time": 287.92 },
    { "id": 39, "time": 288.88 },
    { "id": 40, "time": 289.87 },
    { "id": 41, "time": 290.86 },
    { "id": 42, "time": 291.8 },
    { "id": 43, "time": 292.76 },
    { "id": 44, "time": 293.69 },
    { "id": 45, "time": 294.7 },
    { "id": 46, "time": 295.66 },
    { "id": 47, "time": 296.63 },
    { "id": 48, "time": 297.6 },
    { "id": 49, "time": 298.56 },
    { "id": 50, "time": 299.5 },
    { "id": 51, "time": 300.45 },
    { "id": 52, "time": 301.46 },
    { "id": 53, "time": 302.45 },
    { "id": 54, "time": 303.43 },
    { "id": 55, "time": 304.44 },
    { "id": 56, "time": 305.38 },
    { "id": 57, "time": 306.39 },
    { "id": 58, "time": 307.36 },
    { "id": 59, "time": 308.31 },
    { "id": 60, "time": 309.3 },
    { "id": 61, "time": 310.27 },
    { "id": 62, "time": 311.27 },
    { "id": 63, "time": 312.21 },
    { "id": 64, "time": 313.17 },
    { "id": 65, "time": 314.18 },
    { "id": 66, "time": 315.26 },
    { "id": 67, "time": 316.34 },
    { "id": 68, "time": 317.36 },
    { "id": 69, "time": 318.31 },
    { "id": 70, "time": 319.3 },
    { "id": 71, "time": 320.32 },
    { "id": 72, "time": 321.36 },
    { "id": 73, "time": 322.38 },
    { "id": 74, "time": 323.42 },
    { "id": 75, "time": 324.45 },
    { "id": 76, "time": 325.42 },
    { "id": 77, "time": 326.42 },
    { "id": 78, "time": 327.39 },
    { "id": 79, "time": 328.41 },
    { "id": 80, "time": 329.43 },
    { "id": 81, "time": 330.42 },
    { "id": 82, "time": 331.37 },
    { "id": 83, "time": 332.36 },
    { "id": 84, "time": 333.36 },
    { "id": 85, "time": 334.33 },
    { "id": 86, "time": 335.33 },
    { "id": 87, "time": 336.26 },
    { "id": 88, "time": 337.27 },
    { "id": 89, "time": 338.27 },
    { "id": 90, "time": 339.27 },
    { "id": 91, "time": 340.25 },
    { "id": 92, "time": 341.25 },
    { "id": 93, "time": 342.2 },
    { "id": 94, "time": 343.19 },
    { "id": 95, "time": 344.17 },
    { "id": 96, "time": 345.15 },
    { "id": 97, "time": 346.11 },
    { "id": 98, "time": 347.11 },
    { "id": 99, "time": 348.04 },
    { "id": 100, "time": 349.02 },
    { "id": 101, "time": 350.04 },
    { "id": 102, "time": 351.08 },
    { "id": 103, "time": 352.08 },
    { "id": 104, "time": 352.99 },
    { "id": 105, "time": 353.98 },
    { "id": 106, "time": 354.97 },
    { "id": 107, "time": 355.95 },
    { "id": 108, "time": 356.98 },
    { "id": 109, "time": 357.98 },
    { "id": 110, "time": 359.01 },
    { "id": 111, "time": 359.98 },
    { "id": 112, "time": 360.99 },
    { "id": 113, "time": 361.94 },
    { "id": 114, "time": 362.92 },
    { "id": 115, "time": 363.9 },
    { "id": 116, "time": 364.87 },
    { "id": 117, "time": 365.84 },
    { "id": 118, "time": 366.81 },
    { "id": 119, "time": 367.78 },
    { "id": 120, "time": 368.78 },
    { "id": 121, "time": 369.78 },
    { "id": 122, "time": 370.73 },
    { "id": 123, "time": 371.7 },
    { "id": 124, "time": 372.7 },
    { "id": 125, "time": 373.68 },
    { "id": 126, "time": 374.7 },
    { "id": 127, "time": 375.73 },
    { "id": 128, "time": 376.73 },
    { "id": 129, "time": 377.74 },
    { "id": 130, "time": 378.76 },
    { "id": 131, "time": 379.74 },
    { "id": 132, "time": 380.77 },
    { "id": 133, "time": 381.76 },
    { "id": 134, "time": 382.78 },
    { "id": 135, "time": 383.78 },
    { "id": 136, "time": 384.73 },
    { "id": 137, "time": 385.71 },
    { "id": 138, "time": 386.74 },
    { "id": 139, "time": 387.73 },
    { "id": 140, "time": 388.69 },
    { "id": 141, "time": 389.68 },
    { "id": 142, "time": 390.66 },
    { "id": 143, "time": 391.58 },
    { "id": 144, "time": 392.58 },
    { "id": 145, "time": 393.52 },
    { "id": 146, "time": 394.49 },
    { "id": 147, "time": 395.48 },
    { "id": 148, "time": 396.45 },
    { "id": 149, "time": 397.43 },
    { "id": 150, "time": 398.39 },
    { "id": 151, "time": 399.38 },
    { "id": 152, "time": 400.33 },
    { "id": 153, "time": 401.33 },
    { "id": 154, "time": 402.34 },
    { "id": 155, "time": 403.32 },
    { "id": 156, "time": 404.26 },
    { "id": 157, "time": 405.28 },
    { "id": 158, "time": 406.24 },
    { "id": 159, "time": 407.18 },
    { "id": 160, "time": 408.14 },
    { "id": 161, "time": 409.09 },
    { "id": 162, "time": 410.04 },
    { "id": 163, "time": 410.99 },
    { "id": 164, "time": 411.95 },
    { "id": 165, "time": 412.88 },
    { "id": 166, "time": 413.86 },
    { "id": 167, "time": 414.85 },
    { "id": 168, "time": 415.78 },
    { "id": 169, "time": 416.74 },
    { "id": 170, "time": 417.67 },
    { "id": 171, "time": 418.64 },
    { "id": 172, "time": 419.61 },
    { "id": 173, "time": 420.52 },
    { "id": 174, "time": 421.46 },
    { "id": 175, "time": 422.51 },
    { "id": 176, "time": 423.47 },
    { "id": 177, "time": 424.42 },
    { "id": 178, "time": 425.32 },
    { "id": 179, "time": 426.26 },
    { "id": 180, "time": 427.23 },
    { "id": 181, "time": 428.19 },
    { "id": 182, "time": 429.17 },
    { "id": 183, "time": 430.12 },
    { "id": 184, "time": 431.11 },
    { "id": 185, "time": 432.04 },
    { "id": 186, "time": 433.01 },
    { "id": 187, "time": 433.96 },
    { "id": 188, "time": 434.93 },
    { "id": 189, "time": 435.92 },
    { "id": 190, "time": 436.94 },
    { "id": 191, "time": 437.83 },
    { "id": 192, "time": 438.83 },
    { "id": 193, "time": 439.85 },
    { "id": 194, "time": 442.25 },
    { "id": 195, "time": 443.33 },
    { "id": 196, "time": 444.34 },
    { "id": 197, "time": 445.32 },
    { "id": 198, "time": 446.34 },
    { "id": 199, "time": 447.35 },
    { "id": 200, "time": 448.35 },
    { "id": 201, "time": 449.36 },
    { "id": 202, "time": 450.45 },
    { "id": 203, "time": 451.46 },
    { "id": 204, "time": 452.45 },
    { "id": 205, "time": 453.41 },
    { "id": 206, "time": 454.43 },
    { "id": 207, "time": 455.36 },
    { "id": 208, "time": 456.34 },
    { "id": 209, "time": 457.38 },
    { "id": 210, "time": 458.38 },
    { "id": 211, "time": 459.36 },
    { "id": 212, "time": 460.35 },
    { "id": 213, "time": 461.31 },
    { "id": 214, "time": 462.32 },
    { "id": 215, "time": 463.3 },
    { "id": 216, "time": 464.28 },
    { "id": 217, "time": 465.25 },
    { "id": 218, "time": 466.13 },
    { "id": 219, "time": 467.16 },
    { "id": 220, "time": 468.08 },
    { "id": 221, "time": 469.05 },
    { "id": 222, "time": 469.98 },
    { "id": 223, "time": 470.93 },
    { "id": 224, "time": 471.91 },
    { "id": 225, "time": 472.86 },
    { "id": 226, "time": 473.81 },
    { "id": 227, "time": 474.76 },
    { "id": 228, "time": 475.76 },
    { "id": 229, "time": 476.7 },
    { "id": 230, "time": 477.66 },
    { "id": 231, "time": 478.64 },
    { "id": 232, "time": 479.57 },
    { "id": 233, "time": 480.56 },
    { "id": 234, "time": 481.46 },
    { "id": 235, "time": 482.41 },
    { "id": 236, "time": 483.41 },
    { "id": 237, "time": 484.41 },
    { "id": 238, "time": 485.42 },
    { "id": 239, "time": 486.41 },
    { "id": 240, "time": 487.44 },
    { "id": 241, "time": 488.49 },
    { "id": 242, "time": 489.49 },
    { "id": 243, "time": 490.55 },
    { "id": 244, "time": 491.49 },
    { "id": 245, "time": 492.47 },
    { "id": 246, "time": 493.45 },
    { "id": 247, "time": 494.47 },
    { "id": 248, "time": 495.46 },
    { "id": 249, "time": 496.52 },
    { "id": 250, "time": 497.55 },
    { "id": 251, "time": 498.55 },
    { "id": 252, "time": 499.56 },
    { "id": 253, "time": 500.54 },
    { "id": 254, "time": 501.55 },
    { "id": 255, "time": 502.55 },
    { "id": 256, "time": 503.57 },
    { "id": 257, "time": 504.55 },
    { "id": 258, "time": 505.59 },
    { "id": 259, "time": 506.53 },
    { "id": 260, "time": 507.44 },
    { "id": 261, "time": 508.43 },
    { "id": 262, "time": 509.4 },
    { "id": 263, "time": 510.38 },
    { "id": 264, "time": 511.33 },
    { "id": 265, "time": 512.3 },
    { "id": 266, "time": 513.26 },
    { "id": 267, "time": 514.24 },
    { "id": 268, "time": 515.17 },
    { "id": 269, "time": 516.16 },
    { "id": 270, "time": 517.12 },
    { "id": 271, "time": 518.08 },
    { "id": 272, "time": 519.04 },
    { "id": 273, "time": 520.04 },
    { "id": 274, "time": 521.05 },
    { "id": 275, "time": 522.09 },
    { "id": 276, "time": 523.12 },
    { "id": 277, "time": 524.11 },
    { "id": 278, "time": 525.14 },
    { "id": 279, "time": 526.1 },
    { "id": 280, "time": 527.05 },
    { "id": 281, "time": 528.05 },
    { "id": 282, "time": 529 },
    { "id": 283, "time": 529.94 },
    { "id": 284, "time": 530.87 },
    { "id": 285, "time": 531.86 },
    { "id": 286, "time": 532.85 },
    { "id": 287, "time": 533.78 },
    { "id": 288, "time": 534.72 },
    { "id": 289, "time": 535.68 },
    { "id": 290, "time": 536.63 },
    { "id": 291, "time": 537.61 },
    { "id": 292, "time": 538.54 },
    { "id": 293, "time": 539.47 },
    { "id": 294, "time": 540.43 },
    { "id": 295, "time": 541.59 },
    { "id": 9901, "time": 547 },
    { "id": 9802, "time": 570 },
    { "id": 1001, "time": 575 },
    { "id": 1002, "time": 577.34 },
    { "id": 1003, "time": 580.15 },
    { "id": 1004, "time": 582.37 },
    { "id": 1005, "time": 584.78 },
    { "id": 1006, "time": 587.09 },
    { "id": 1007, "time": 589.42 },
    { "id": 1008, "time": 591.68 },
    { "id": 1001, "time": 594.22 },
    { "id": 1002, "time": 596.56 },
    { "id": 1003, "time": 599.19 },
    { "id": 1004, "time": 601.42 },
    { "id": 1005, "time": 603.88 },
    { "id": 1006, "time": 606.18 },
    { "id": 1007, "time": 608.45 },
    { "id": 1008, "time": 610.71 },
    { "id": 1009, "time": 613.06 },
    { "id": 1010, "time": 615.47 },
    { "id": 1011, "time": 617.72 },
    { "id": 1012, "time": 619.99 },
    { "id": 1013, "time": 622.17 },
    { "id": 1014, "time": 624.37 },
    { "id": 1015, "time": 626.55 },
    { "id": 1016, "time": 628.77 },
    { "id": 1017, "time": 631.54 },
    { "id": 1018, "time": 633.88 },
    { "id": 1019, "time": 636.37 },
    { "id": 1020, "time": 638.61 },
    { "id": 1021, "time": 641.02 },
    { "id": 1022, "time": 643.33 },
    { "id": 1023, "time": 645.73 },
    { "id": 1024, "time": 648.2 },
    { "id": 1025, "time": 651.36 },
    { "id": 1026, "time": 658.64 },
    { "id": 1027, "time": 661.2 },
    { "id": 1028, "time": 663.63 },
    { "id": 1029, "time": 665.99 },
    { "id": 1030, "time": 668.47 },
    { "id": 1031, "time": 670.75 },
    { "id": 1032, "time": 673.09 },
    { "id": 1033, "time": 675.53 },
    { "id": 1034, "time": 678.09 },
    { "id": 1035, "time": 680.47 },
    { "id": 1036, "time": 682.98 },
    { "id": 1037, "time": 685.51 },
    { "id": 1009, "time": 688.17 },
    { "id": 1010, "time": 690.7 },
    { "id": 1011, "time": 693.04 },
    { "id": 1012, "time": 695.5 },
    { "id": 1013, "time": 697.77 },
    { "id": 1014, "time": 700.12 },
    { "id": 1015, "time": 702.44 },
    { "id": 1016, "time": 704.77 },
    { "id": 1017, "time": 707.74 },
    { "id": 1018, "time": 710.25 },
    { "id": 1019, "time": 712.81 },
    { "id": 1020, "time": 715.16 },
    { "id": 1021, "time": 717.63 },
    { "id": 1022, "time": 720.04 },
    { "id": 1023, "time": 722.56 },
    { "id": 1024, "time": 725.07 },
    { "id": 1025, "time": 728.33 },
    { "id": 1026, "time": 736.49 },
    { "id": 1027, "time": 739.05 },
    { "id": 1028, "time": 741.54 },
    { "id": 1029, "time": 743.88 },
    { "id": 1030, "time": 746.49 },
    { "id": 1031, "time": 748.78 },
    { "id": 1032, "time": 751.13 },
    { "id": 1033, "time": 753.81 },
    { "id": 1034, "time": 756.23 },
    { "id": 1035, "time": 758.85 },
    { "id": 1036, "time": 761.23 },
    { "id": 1037, "time": 763.8 },
    { "id": 1038, "time": 766.6 },
    { "id": 1039, "time": 768.95 },
    { "id": 1040, "time": 771.27 },
    { "id": 1041, "time": 773.68 },
    { "id": 1042, "time": 776.35 },
    { "id": 1043, "time": 778.56 },
    { "id": 1044, "time": 780.75 },
    { "id": 1045, "time": 782.89 },
    { "id": 1046, "time": 785.04 },
    { "id": 1047, "time": 787.14 },
    { "id": 1048, "time": 789.25 },
    { "id": 1049, "time": 791.28 },
    { "id": 1050, "time": 793.37 },
    { "id": 1051, "time": 795.4 },
    { "id": 1052, "time": 797.49 },
    { "id": 1053, "time": 799.57 },
    { "id": 1054, "time": 801.66 },
    { "id": 1055, "time": 803.74 },
    { "id": 1056, "time": 805.79 },
    { "id": 1057, "time": 809.06 },
    { "id": 1058, "time": 811.27 },
    { "id": 1059, "time": 813.75 },
    { "id": 1060, "time": 816.07 },
    { "id": 1061, "time": 818.24 },
    { "id": 1062, "time": 820.4 },
    { "id": 1063, "time": 822.53 },
    { "id": 1064, "time": 824.67 },
    { "id": 1065, "time": 826.82 },
    { "id": 1066, "time": 828.97 },
    { "id": 1067, "time": 831.1 },
    { "id": 1068, "time": 833.29 },
    { "id": 1069, "time": 835.4 },
    { "id": 1070, "time": 837.5 },
    { "id": 1071, "time": 839.54 },
    { "id": 1072, "time": 841.59 },
    { "id": 1073, "time": 843.66 },
    { "id": 1074, "time": 845.8 },
    { "id": 1075, "time": 847.9 },
    { "id": 1076, "time": 850.3 },
    { "id": 1077, "time": 852.49 },
    { "id": 1078, "time": 854.69 },
    { "id": 1079, "time": 856.92 },
    { "id": 1080, "time": 859.21 },
    { "id": 1081, "time": 861.44 },
    { "id": 1082, "time": 863.8 },
    { "id": 1083, "time": 866.12 },
    { "id": 1084, "time": 868.41 },
    { "id": 1085, "time": 870.51 },
    { "id": 1086, "time": 872.86 },
    { "id": 1087, "time": 875.29 },
    { "id": 1088, "time": 877.46 },
    { "id": 1089, "time": 879.57 },
    { "id": 1090, "time": 884.52 },
    { "id": 1091, "time": 886.79 },
    { "id": 1092, "time": 889.09 },
    { "id": 1093, "time": 891.41 },
    { "id": 1094, "time": 893.59 },
    { "id": 1095, "time": 895.83 },
    { "id": 1096, "time": 898.07 },
    { "id": 1097, "time": 900.41 },
    { "id": 1098, "time": 902.94 },
    { "id": 1099, "time": 905.3 },
    { "id": 1100, "time": 907.51 },
    { "id": 1101, "time": 909.76 },
    { "id": 1102, "time": 912.05 },
    { "id": 1103, "time": 914.29 },
    { "id": 1104, "time": 916.48 },
    { "id": 1105, "time": 918.62 },
    { "id": 1106, "time": 920.78 },
    { "id": 1107, "time": 922.97 },
    { "id": 1108, "time": 925.07 },
    { "id": 1109, "time": 927.27 },
    { "id": 1110, "time": 929.35 },
    { "id": 1111, "time": 931.56 },
    { "id": 1112, "time": 933.78 },
    { "id": 1113, "time": 936.84 },
    { "id": 1114, "time": 943.97 },
    { "id": 1115, "time": 946.47 },
    { "id": 1116, "time": 950.79 },
    { "id": 1117, "time": 953.34 },
    { "id": 1118, "time": 957.98 },
    { "id": 1119, "time": 960.38 },
    { "id": 1120, "time": 962.75 },
    { "id": 1121, "time": 965.18 },
    { "id": 1122, "time": 967.64 },
    { "id": 1123, "time": 969.95 },
    { "id": 1124, "time": 972.27 },
    { "id": 1125, "time": 974.4 },
    { "id": 1126, "time": 976.73 },
    { "id": 1127, "time": 978.91 },
    { "id": 1128, "time": 981.08 },
    { "id": 1129, "time": 983.34 },
    { "id": 1130, "time": 985.61 },
    { "id": 1131, "time": 987.72 },
    { "id": 1132, "time": 989.88 },
    { "id": 1133, "time": 992.05 },
    { "id": 1134, "time": 994.24 },
    { "id": 1135, "time": 996.64 },
    { "id": 1136, "time": 998.97 },
    { "id": 1137, "time": 1001.22 },
    { "id": 1138, "time": 1003.56 },
    { "id": 1139, "time": 1005.72 },
    { "id": 1140, "time": 1007.84 },
    { "id": 1141, "time": 1010.2 },
    { "id": 1142, "time": 1012.51 },
    { "id": 1143, "time": 1014.74 },
    { "id": 1144, "time": 1017.05 },
    { "id": 1145, "time": 1019.36 },
    { "id": 1146, "time": 1021.64 },
    { "id": 1147, "time": 1023.92 },
    { "id": 1148, "time": 1026.15 },
    { "id": 1149, "time": 1028.5 },
    { "id": 1150, "time": 1030.84 },
    { "id": 1151, "time": 1033.07 },
    { "id": 1152, "time": 1035.74 },
    { "id": 9902, "time": 1040 },
    { "id": 9803, "time": 1064 },
    { "id": 2000, "time": 1067.02 },
    { "id": 2001, "time": 1067.33 },
    { "id": 2002, "time": 1068.31 },
    { "id": 2003, "time": 1069.23 },
    { "id": 2004, "time": 1070.15 },
    { "id": 2005, "time": 1071.06 },
    { "id": 2006, "time": 1072 },
    { "id": 2007, "time": 1072.91 },
    { "id": 2008, "time": 1073.81 },
    { "id": 2009, "time": 1074.82 },
    { "id": 2010, "time": 1075.77 },
    { "id": 2011, "time": 1076.7 },
    { "id": 2012, "time": 1077.62 },
    { "id": 2013, "time": 1078.56 },
    { "id": 2014, "time": 1079.49 },
    { "id": 2015, "time": 1080.4 },
    { "id": 2016, "time": 1081.38 },
    { "id": 2017, "time": 1081.93 },
    { "id": 2018, "time": 1082.34 },
    { "id": 2019, "time": 1083.3 },
    { "id": 2020, "time": 1084.18 },
    { "id": 2021, "time": 1085.1 },
    { "id": 2022, "time": 1086.02 },
    { "id": 2023, "time": 1086.94 },
    { "id": 2024, "time": 1087.85 },
    { "id": 2025, "time": 1088.77 },
    { "id": 2026, "time": 1089.69 },
    { "id": 2027, "time": 1090.55 },
    { "id": 2028, "time": 1091.52 },
    { "id": 2029, "time": 1092.45 },
    { "id": 2030, "time": 1093.35 },
    { "id": 2031, "time": 1094.26 },
    { "id": 2032, "time": 1095.2 },
    { "id": 2033, "time": 1096.11 },
    { "id": 2034, "time": 1097.02 },
    { "id": 2035, "time": 1097.96 },
    { "id": 2036, "time": 1098.9 },
    { "id": 2037, "time": 1099.85 },
    { "id": 2038, "time": 1100.77 },
    { "id": 2039, "time": 1101.66 },
    { "id": 2040, "time": 1102.55 },
    { "id": 2041, "time": 1103.51 },
    { "id": 2042, "time": 1104.42 },
    { "id": 2043, "time": 1105.37 },
    { "id": 2044, "time": 1106.27 },
    { "id": 2045, "time": 1107.23 },
    { "id": 2046, "time": 1108.17 },
    { "id": 2047, "time": 1109.02 },
    { "id": 2048, "time": 1109.94 },
    { "id": 2049, "time": 1110.87 },
    { "id": 2050, "time": 1111.74 },
    { "id": 2051, "time": 1112.65 },
    { "id": 2052, "time": 1113.53 },
    { "id": 2053, "time": 1114.5 },
    { "id": 2017, "time": 1115.1 },
    { "id": 2018, "time": 1115.46 },
    { "id": 2019, "time": 1116.36 },
    { "id": 2020, "time": 1117.26 },
    { "id": 2021, "time": 1118.22 },
    { "id": 2022, "time": 1119.22 },
    { "id": 2023, "time": 1120.07 },
    { "id": 2024, "time": 1120.98 },
    { "id": 2025, "time": 1121.89 },
    { "id": 2026, "time": 1122.81 },
    { "id": 2027, "time": 1123.71 },
    { "id": 2028, "time": 1124.66 },
    { "id": 2029, "time": 1125.6 },
    { "id": 2030, "time": 1126.54 },
    { "id": 2031, "time": 1127.43 },
    { "id": 2032, "time": 1128.41 },
    { "id": 2033, "time": 1129.29 },
    { "id": 2034, "time": 1130.17 },
    { "id": 2035, "time": 1131.14 },
    { "id": 2036, "time": 1132.12 },
    { "id": 2037, "time": 1133.02 },
    { "id": 2038, "time": 1133.94 },
    { "id": 2039, "time": 1134.85 },
    { "id": 2040, "time": 1135.74 },
    { "id": 2041, "time": 1136.68 },
    { "id": 2042, "time": 1137.54 },
    { "id": 2043, "time": 1138.55 },
    { "id": 2044, "time": 1139.43 },
    { "id": 2045, "time": 1140.37 },
    { "id": 2046, "time": 1141.3 },
    { "id": 2047, "time": 1142.1 },
    { "id": 2048, "time": 1143.02 },
    { "id": 2049, "time": 1143.81 },
    { "id": 2050, "time": 1144.8 },
    { "id": 2051, "time": 1145.75 },
    { "id": 2052, "time": 1146.66 },
    { "id": 2053, "time": 1147.61 },
    { "id": 2054, "time": 1148.86 },
    { "id": 2055, "time": 1149.69 },
    { "id": 2056, "time": 1151.76 },
    { "id": 2057, "time": 1154.16 },
    { "id": 2058, "time": 1155.29 },
    { "id": 2059, "time": 1156.29 },
    { "id": 2060, "time": 1157.28 },
    { "id": 2061, "time": 1158.29 },
    { "id": 2062, "time": 1159.28 },
    { "id": 2063, "time": 1160.22 },
    { "id": 2064, "time": 1161.17 },
    { "id": 2065, "time": 1162.08 },
    { "id": 2066, "time": 1163.09 },
    { "id": 2054, "time": 1163.77 },
    { "id": 2055, "time": 1164.34 },
    { "id": 2056, "time": 1166.29 },
    { "id": 2057, "time": 1168.63 },
    { "id": 2058, "time": 1169.71 },
    { "id": 2059, "time": 1170.68 },
    { "id": 2060, "time": 1171.64 },
    { "id": 2061, "time": 1172.64 },
    { "id": 2062, "time": 1173.54 },
    { "id": 2063, "time": 1174.53 },
    { "id": 2064, "time": 1175.51 },
    { "id": 2065, "time": 1176.47 },
    { "id": 2066, "time": 1177.46 },
    { "id": 2067, "time": 1178.13 },
    { "id": 2068, "time": 1178.48 },
    { "id": 2069, "time": 1179.48 },
    { "id": 2070, "time": 1180.43 },
    { "id": 2071, "time": 1181.4 },
    { "id": 2072, "time": 1182.36 },
    { "id": 2073, "time": 1183.32 },
    { "id": 2074, "time": 1184.29 },
    { "id": 2075, "time": 1185.21 },
    { "id": 2076, "time": 1186.24 },
    { "id": 2077, "time": 1187.31 },
    { "id": 2078, "time": 1188.42 },
    { "id": 2079, "time": 1189.38 },
    { "id": 2080, "time": 1190.38 },
    { "id": 2081, "time": 1191.36 },
    { "id": 2082, "time": 1192.48 },
    { "id": 2083, "time": 1194.4 },
    { "id": 2084, "time": 1196.97 },
    { "id": 2085, "time": 1198.03 },
    { "id": 2086, "time": 1199 },
    { "id": 2087, "time": 1199.91 },
    { "id": 2088, "time": 1200.83 },
    { "id": 2089, "time": 1201.73 },
    { "id": 2090, "time": 1202.81 },
    { "id": 2091, "time": 1203.9 },
    { "id": 2092, "time": 1205.16 },
    { "id": 2093, "time": 1206.25 },
    { "id": 2094, "time": 1207.26 },
    { "id": 2095, "time": 1208.23 },
    { "id": 2096, "time": 1209.3 },
    { "id": 2097, "time": 1210.29 },
    { "id": 2067, "time": 1211.02 },
    { "id": 2068, "time": 1211.39 },
    { "id": 2069, "time": 1212.34 },
    { "id": 2070, "time": 1213.29 },
    { "id": 2071, "time": 1214.25 },
    { "id": 2072, "time": 1215.18 },
    { "id": 2073, "time": 1216.13 },
    { "id": 2074, "time": 1217.09 },
    { "id": 2075, "time": 1218.02 },
    { "id": 2076, "time": 1219.08 },
    { "id": 2077, "time": 1220.07 },
    { "id": 2078, "time": 1221.08 },
    { "id": 2079, "time": 1222.05 },
    { "id": 2080, "time": 1223.03 },
    { "id": 2081, "time": 1224.07 },
    { "id": 2082, "time": 1225.16 },
    { "id": 2083, "time": 1227.16 },
    { "id": 2084, "time": 1229.68 },
    { "id": 2085, "time": 1230.66 },
    { "id": 2086, "time": 1231.63 },
    { "id": 2087, "time": 1232.59 },
    { "id": 2088, "time": 1233.61 },
    { "id": 2089, "time": 1234.49 },
    { "id": 2090, "time": 1235.47 },
    { "id": 2091, "time": 1236.56 },
    { "id": 2092, "time": 1237.84 },
    { "id": 2093, "time": 1238.89 },
    { "id": 2094, "time": 1239.91 },
    { "id": 2095, "time": 1240.9 },
    { "id": 2096, "time": 1241.94 },
    { "id": 2097, "time": 1243.01 },
    { "id": 2098, "time": 1243.62 },
    { "id": 2099, "time": 1244.1 },
    { "id": 2100, "time": 1245.16 },
    { "id": 2101, "time": 1246.11 },
    { "id": 2102, "time": 1247.15 },
    { "id": 2103, "time": 1248.13 },
    { "id": 2104, "time": 1249.13 },
    { "id": 2105, "time": 1250.09 },
    { "id": 2106, "time": 1251.05 },
    { "id": 2107, "time": 1252.07 },
    { "id": 2108, "time": 1253.86 },
    { "id": 2000, "time": 1257.5 },
    { "id": 2001, "time": 1257.93 },
    { "id": 2002, "time": 1258.86 },
    { "id": 2003, "time": 1259.77 },
    { "id": 2004, "time": 1260.69 },
    { "id": 2005, "time": 1261.62 },
    { "id": 2006, "time": 1262.54 },
    { "id": 2007, "time": 1263.49 },
    { "id": 2008, "time": 1264.44 },
    { "id": 2009, "time": 1265.5 },
    { "id": 2010, "time": 1266.4 },
    { "id": 2011, "time": 1267.31 },
    { "id": 2012, "time": 1268.23 },
    { "id": 2013, "time": 1269.16 },
    { "id": 2014, "time": 1270.14 },
    { "id": 2015, "time": 1271.04 },
    { "id": 2016, "time": 1271.97 },
    { "id": 2017, "time": 1272.59 },
    { "id": 2018, "time": 1272.95 },
    { "id": 2019, "time": 1273.89 },
    { "id": 2020, "time": 1274.82 },
    { "id": 2021, "time": 1275.72 },
    { "id": 2022, "time": 1276.66 },
    { "id": 2023, "time": 1277.58 },
    { "id": 2024, "time": 1278.53 },
    { "id": 2025, "time": 1279.41 },
    { "id": 2026, "time": 1280.33 },
    { "id": 2027, "time": 1281.22 },
    { "id": 2028, "time": 1282.21 },
    { "id": 2029, "time": 1283.12 },
    { "id": 2030, "time": 1284.03 },
    { "id": 2031, "time": 1284.95 },
    { "id": 2032, "time": 1285.92 },
    { "id": 2033, "time": 1286.8 },
    { "id": 2034, "time": 1287.77 },
    { "id": 2035, "time": 1288.7 },
    { "id": 2036, "time": 1289.64 },
    { "id": 2037, "time": 1290.54 },
    { "id": 2038, "time": 1291.47 },
    { "id": 2039, "time": 1292.37 },
    { "id": 2040, "time": 1293.25 },
    { "id": 2041, "time": 1294.18 },
    { "id": 2042, "time": 1295.1 },
    { "id": 2043, "time": 1296.06 },
    { "id": 2044, "time": 1296.97 },
    { "id": 2045, "time": 1297.93 },
    { "id": 2046, "time": 1298.84 },
    { "id": 2047, "time": 1299.67 },
    { "id": 2048, "time": 1300.5 },
    { "id": 2049, "time": 1301.38 },
    { "id": 2050, "time": 1302.25 },
    { "id": 2051, "time": 1303.19 },
    { "id": 2052, "time": 1304.09 },
    { "id": 2053, "time": 1305.29 },
    { "id": 9903, "time": 1308 },
    { "id": 9804, "time": 1320 },
    { "id": 3001, "time": 1322.5 },
    { "id": 3002, "time": 1323.39 },
    { "id": 3003, "time": 1324.21 },
    { "id": 3004, "time": 1325.06 },
    { "id": 3005, "time": 1325.91 },
    { "id": 3006, "time": 1326.69 },
    { "id": 3007, "time": 1327.51 },
    { "id": 3008, "time": 1328.33 },
    { "id": 3009, "time": 1329.17 },
    { "id": 3010, "time": 1329.91 },
    { "id": 3011, "time": 1330.8 },
    { "id": 3012, "time": 1331.63 },
    { "id": 3013, "time": 1332.48 },
    { "id": 3014, "time": 1333.34 },
    { "id": 3015, "time": 1334.13 },
    { "id": 3016, "time": 1334.94 },
    { "id": 3017, "time": 1335.72 },
    { "id": 3018, "time": 1336.54 },
    { "id": 3019, "time": 1337.39 },
    { "id": 3020, "time": 1338.2 },
    { "id": 3021, "time": 1339.04 },
    { "id": 3022, "time": 1339.87 },
    { "id": 3023, "time": 1340.7 },
    { "id": 3024, "time": 1341.51 },
    { "id": 3025, "time": 1342.3 },
    { "id": 3026, "time": 1343.15 },
    { "id": 3027, "time": 1343.95 },
    { "id": 3028, "time": 1344.75 },
    { "id": 3029, "time": 1345.55 },
    { "id": 3030, "time": 1346.42 },
    { "id": 3031, "time": 1347.19 },
    { "id": 3032, "time": 1348.11 },
    { "id": 3033, "time": 1348.98 },
    { "id": 3034, "time": 1349.8 },
    { "id": 3035, "time": 1350.62 },
    { "id": 3036, "time": 1351.49 },
    { "id": 3037, "time": 1352.31 },
    { "id": 3038, "time": 1353.13 },
    { "id": 3039, "time": 1353.93 },
    { "id": 3040, "time": 1354.77 },
    { "id": 3041, "time": 1355.62 },
    { "id": 3042, "time": 1356.47 },
    { "id": 3043, "time": 1357.25 },
    { "id": 3044, "time": 1358.1 },
    { "id": 3045, "time": 1358.94 },
    { "id": 3046, "time": 1359.78 },
    { "id": 3047, "time": 1360.67 },
    { "id": 3048, "time": 1361.44 },
    { "id": 3049, "time": 1362.24 },
    { "id": 3050, "time": 1363.06 },
    { "id": 3051, "time": 1363.92 },
    { "id": 3052, "time": 1364.75 },
    { "id": 3053, "time": 1365.58 },
    { "id": 3054, "time": 1366.42 },
    { "id": 3055, "time": 1367.22 },
    { "id": 3056, "time": 1368.11 },
    { "id": 3057, "time": 1368.96 },
    { "id": 3058, "time": 1369.79 },
    { "id": 3059, "time": 1370.65 },
    { "id": 3060, "time": 1371.47 },
    { "id": 3061, "time": 1372.28 },
    { "id": 3062, "time": 1373.13 },
    { "id": 3063, "time": 1373.96 },
    { "id": 3064, "time": 1374.78 },
    { "id": 3065, "time": 1375.57 },
    { "id": 3066, "time": 1376.39 },
    { "id": 3067, "time": 1377.25 },
    { "id": 3068, "time": 1378.08 },
    { "id": 3069, "time": 1378.92 },
    { "id": 3070, "time": 1379.82 },
    { "id": 3071, "time": 1380.63 },
    { "id": 3072, "time": 1381.46 },
    { "id": 3073, "time": 1382.32 },
    { "id": 3074, "time": 1383.17 },
    { "id": 3075, "time": 1384 },
    { "id": 3076, "time": 1384.83 },
    { "id": 3077, "time": 1385.67 },
    { "id": 3078, "time": 1386.51 },
    { "id": 3079, "time": 1387.32 },
    { "id": 3080, "time": 1388.2 },
    { "id": 3081, "time": 1388.98 },
    { "id": 3082, "time": 1389.81 },
    { "id": 3083, "time": 1390.66 },
    { "id": 3084, "time": 1391.59 },
    { "id": 3085, "time": 1392.5 },
    { "id": 3086, "time": 1393.38 },
    { "id": 3087, "time": 1394.29 },
    { "id": 3088, "time": 1395.19 },
    { "id": 3089, "time": 1396.05 },
    { "id": 3090, "time": 1396.9 },
    { "id": 3091, "time": 1397.74 },
    { "id": 3092, "time": 1398.64 },
    { "id": 3093, "time": 1399.51 },
    { "id": 3094, "time": 1400.38 },
    { "id": 3095, "time": 1401.25 },
    { "id": 3096, "time": 1402.13 },
    { "id": 3097, "time": 1403.02 },
    { "id": 3098, "time": 1403.94 },
    { "id": 3099, "time": 1404.88 },
    { "id": 3100, "time": 1405.91 },
    { "id": 3101, "time": 1406.86 },
    { "id": 3102, "time": 1407.75 },
    { "id": 3103, "time": 1408.65 },
    { "id": 3104, "time": 1409.52 },
    { "id": 3105, "time": 1410.32 },
    { "id": 3106, "time": 1411.18 },
    { "id": 3107, "time": 1412 },
    { "id": 3108, "time": 1412.85 },
    { "id": 3109, "time": 1413.67 },
    { "id": 3110, "time": 1414.49 },
    { "id": 3111, "time": 1415.3 },
    { "id": 3112, "time": 1416.12 },
    { "id": 3113, "time": 1416.94 },
    { "id": 3114, "time": 1417.77 },
    { "id": 3115, "time": 1418.6 },
    { "id": 3116, "time": 1419.37 },
    { "id": 3117, "time": 1420.22 },
    { "id": 3118, "time": 1421.01 },
    { "id": 3119, "time": 1421.91 },
    { "id": 3120, "time": 1422.73 },
    { "id": 3121, "time": 1423.55 },
    { "id": 3003, "time": 1424.34 },
    { "id": 3004, "time": 1425.19 },
    { "id": 3005, "time": 1426.04 },
    { "id": 3006, "time": 1426.85 },
    { "id": 3007, "time": 1427.69 },
    { "id": 3008, "time": 1428.53 },
    { "id": 3009, "time": 1429.36 },
    { "id": 3010, "time": 1430.15 },
    { "id": 3011, "time": 1431 },
    { "id": 3012, "time": 1431.84 },
    { "id": 3013, "time": 1432.66 },
    { "id": 3014, "time": 1433.49 },
    { "id": 3015, "time": 1434.33 },
    { "id": 3016, "time": 1435.14 },
    { "id": 3017, "time": 1435.94 },
    { "id": 3018, "time": 1436.77 },
    { "id": 3019, "time": 1437.59 },
    { "id": 3020, "time": 1438.43 },
    { "id": 3021, "time": 1439.28 },
    { "id": 3022, "time": 1440.11 },
    { "id": 3023, "time": 1440.96 },
    { "id": 3024, "time": 1441.81 },
    { "id": 3025, "time": 1442.61 },
    { "id": 3026, "time": 1443.45 },
    { "id": 3027, "time": 1444.28 },
    { "id": 3028, "time": 1445.09 },
    { "id": 3029, "time": 1445.89 },
    { "id": 3030, "time": 1446.74 },
    { "id": 3031, "time": 1447.54 },
    { "id": 3032, "time": 1448.46 },
    { "id": 3033, "time": 1449.28 },
    { "id": 3034, "time": 1450.08 },
    { "id": 3035, "time": 1451 },
    { "id": 3036, "time": 1451.84 },
    { "id": 3037, "time": 1452.7 },
    { "id": 3038, "time": 1453.53 },
    { "id": 3039, "time": 1454.36 },
    { "id": 3040, "time": 1455.21 },
    { "id": 3041, "time": 1456.05 },
    { "id": 3042, "time": 1456.9 },
    { "id": 3043, "time": 1457.72 },
    { "id": 3044, "time": 1458.58 },
    { "id": 3045, "time": 1459.45 },
    { "id": 3046, "time": 1460.29 },
    { "id": 3047, "time": 1461.16 },
    { "id": 3048, "time": 1461.97 },
    { "id": 3049, "time": 1462.81 },
    { "id": 3050, "time": 1463.63 },
    { "id": 3051, "time": 1464.48 },
    { "id": 3052, "time": 1465.33 },
    { "id": 3053, "time": 1466.15 },
    { "id": 3054, "time": 1466.97 },
    { "id": 3055, "time": 1467.84 },
    { "id": 3056, "time": 1468.73 },
    { "id": 3057, "time": 1469.57 },
    { "id": 3058, "time": 1470.4 },
    { "id": 3059, "time": 1471.27 },
    { "id": 3060, "time": 1472.09 },
    { "id": 3061, "time": 1472.93 },
    { "id": 3062, "time": 1473.78 },
    { "id": 3063, "time": 1474.65 },
    { "id": 3064, "time": 1475.47 },
    { "id": 3065, "time": 1476.28 },
    { "id": 3066, "time": 1477.15 },
    { "id": 3067, "time": 1477.98 },
    { "id": 3068, "time": 1478.84 },
    { "id": 3069, "time": 1479.65 },
    { "id": 3070, "time": 1480.51 },
    { "id": 3071, "time": 1481.4 },
    { "id": 3072, "time": 1482.26 },
    { "id": 3073, "time": 1483.16 },
    { "id": 3074, "time": 1483.99 },
    { "id": 3075, "time": 1484.83 },
    { "id": 3076, "time": 1485.68 },
    { "id": 3077, "time": 1486.53 },
    { "id": 3078, "time": 1487.35 },
    { "id": 3079, "time": 1488.19 },
    { "id": 3080, "time": 1489.02 },
    { "id": 3081, "time": 1489.82 },
    { "id": 3082, "time": 1490.67 },
    { "id": 3083, "time": 1491.57 },
    { "id": 3084, "time": 1492.5 },
    { "id": 3085, "time": 1493.37 },
    { "id": 3086, "time": 1494.25 },
    { "id": 3087, "time": 1495.04 },
    { "id": 3088, "time": 1495.99 },
    { "id": 3089, "time": 1496.88 },
    { "id": 3090, "time": 1497.74 },
    { "id": 3091, "time": 1498.64 },
    { "id": 3092, "time": 1499.55 },
    { "id": 3093, "time": 1500.44 },
    { "id": 3094, "time": 1501.3 },
    { "id": 3095, "time": 1502.17 },
    { "id": 3096, "time": 1503.04 },
    { "id": 3097, "time": 1503.95 },
    { "id": 3098, "time": 1504.89 },
    { "id": 3099, "time": 1505.88 },
    { "id": 3100, "time": 1506.81 },
    { "id": 3101, "time": 1507.77 },
    { "id": 3102, "time": 1508.73 },
    { "id": 3103, "time": 1509.66 },
    { "id": 3104, "time": 1510.49 },
    { "id": 3105, "time": 1511.32 },
    { "id": 3106, "time": 1512.17 },
    { "id": 3107, "time": 1512.98 },
    { "id": 3108, "time": 1513.81 },
    { "id": 3109, "time": 1514.65 },
    { "id": 3110, "time": 1515.49 },
    { "id": 3111, "time": 1516.28 },
    { "id": 3112, "time": 1517.09 },
    { "id": 3113, "time": 1517.92 },
    { "id": 3114, "time": 1518.73 },
    { "id": 3115, "time": 1519.53 },
    { "id": 3116, "time": 1520.35 },
    { "id": 3117, "time": 1521.18 },
    { "id": 3122, "time": 1521.96 },
    { "id": 3123, "time": 1522.83 },
    { "id": 3124, "time": 1523.75 },
    { "id": 3125, "time": 1524.55 },
    { "id": 3126, "time": 1525.41 },
    { "id": 3127, "time": 1526.23 },
    { "id": 3128, "time": 1527.11 },
    { "id": 3129, "time": 1527.94 },
    { "id": 3130, "time": 1528.78 },
    { "id": 3131, "time": 1529.61 },
    { "id": 3132, "time": 1530.42 },
    { "id": 3133, "time": 1531.26 },
    { "id": 3134, "time": 1532.18 },
    { "id": 3135, "time": 1532.97 },
    { "id": 3136, "time": 1533.88 },
    { "id": 3137, "time": 1534.74 },
    { "id": 3138, "time": 1535.61 },
    { "id": 3139, "time": 1536.44 },
    { "id": 3140, "time": 1537.26 },
    { "id": 3141, "time": 1538.12 },
    { "id": 3142, "time": 1538.97 },
    { "id": 3143, "time": 1539.79 },
    { "id": 3144, "time": 1540.63 },
    { "id": 3145, "time": 1541.48 },
    { "id": 3146, "time": 1542.32 },
    { "id": 3147, "time": 1543.08 },
    { "id": 3148, "time": 1543.97 },
    { "id": 3149, "time": 1544.78 },
    { "id": 3150, "time": 1545.64 },
    { "id": 3151, "time": 1546.46 },
    { "id": 3152, "time": 1547.27 },
    { "id": 3153, "time": 1548.09 },
    { "id": 3154, "time": 1548.94 },
    { "id": 3155, "time": 1549.75 },
    { "id": 3156, "time": 1550.59 },
    { "id": 3157, "time": 1551.4 },
    { "id": 3158, "time": 1552.23 },
    { "id": 3159, "time": 1553.06 },
    { "id": 3160, "time": 1553.87 },
    { "id": 3161, "time": 1554.76 },
    { "id": 3162, "time": 1555.63 },
    { "id": 3163, "time": 1556.44 },
    { "id": 3164, "time": 1557.26 },
    { "id": 3165, "time": 1558.09 },
    { "id": 3166, "time": 1558.92 },
    { "id": 3167, "time": 1559.76 },
    { "id": 3168, "time": 1560.55 },
    { "id": 3169, "time": 1561.4 },
    { "id": 3170, "time": 1562.26 },
    { "id": 3171, "time": 1563.34 },
    { "id": 3172, "time": 1564.29 },
    { "id": 3173, "time": 1565.22 },
    { "id": 3174, "time": 1566.14 },
    { "id": 3175, "time": 1567.03 },
    { "id": 3176, "time": 1567.87 },
    { "id": 3177, "time": 1568.7 },
    { "id": 3178, "time": 1569.66 },
    { "id": 3179, "time": 1570.55 },
    { "id": 3180, "time": 1571.46 },
    { "id": 3181, "time": 1572.3 },
    { "id": 3182, "time": 1573.17 },
    { "id": 3183, "time": 1574.08 },
    { "id": 3184, "time": 1574.97 },
    { "id": 3185, "time": 1575.89 },
    { "id": 3186, "time": 1576.89 },
    { "id": 3187, "time": 1577.97 },
    { "id": 3188, "time": 1578.99 },
    { "id": 3189, "time": 1579.99 },
    { "id": 3190, "time": 1580.99 },
    { "id": 3191, "time": 1581.86 },
    { "id": 3192, "time": 1582.89 },
    { "id": 3193, "time": 1583.79 },
    { "id": 3194, "time": 1584.71 },
    { "id": 3195, "time": 1585.57 },
    { "id": 3196, "time": 1586.44 },
    { "id": 3197, "time": 1587.46 },
    { "id": 3198, "time": 1588.41 },
    { "id": 3199, "time": 1589.26 },
    { "id": 3200, "time": 1590.1 },
    { "id": 3201, "time": 1590.92 },
    { "id": 3202, "time": 1591.73 },
    { "id": 3203, "time": 1592.56 },
    { "id": 3204, "time": 1593.34 },
    { "id": 3205, "time": 1594.18 },
    { "id": 3206, "time": 1594.97 },
    { "id": 3207, "time": 1595.78 },
    { "id": 3208, "time": 1596.63 },
    { "id": 3209, "time": 1597.49 },
    { "id": 3210, "time": 1598.31 },
    { "id": 3211, "time": 1599.13 },
    { "id": 3212, "time": 1599.97 },
    { "id": 3213, "time": 1600.78 },
    { "id": 3214, "time": 1601.63 },
    { "id": 3215, "time": 1602.41 },
    { "id": 3216, "time": 1603.23 },
    { "id": 3217, "time": 1604.05 },
    { "id": 3218, "time": 1604.86 },
    { "id": 3219, "time": 1605.76 },
    { "id": 3220, "time": 1606.56 },
    { "id": 3221, "time": 1607.36 },
    { "id": 3222, "time": 1608.18 },
    { "id": 3223, "time": 1609.05 },
    { "id": 3224, "time": 1609.86 },
    { "id": 3225, "time": 1610.72 },
    { "id": 3226, "time": 1611.55 },
    { "id": 3227, "time": 1612.42 },
    { "id": 3228, "time": 1613.25 },
    { "id": 3229, "time": 1614.09 },
    { "id": 3230, "time": 1614.9 },
    { "id": 3231, "time": 1615.74 },
    { "id": 3232, "time": 1616.58 },
    { "id": 3233, "time": 1617.45 },
    { "id": 3234, "time": 1618.3 },
    { "id": 3235, "time": 1619.12 },
    { "id": 3236, "time": 1620.01 },
    { "id": 3237, "time": 1620.87 },
    { "id": 3238, "time": 1621.73 },
    { "id": 3239, "time": 1622.54 },
    { "id": 3240, "time": 1623.36 },
    { "id": 3241, "time": 1624.21 },
    { "id": 3242, "time": 1625.02 },
    { "id": 3243, "time": 1625.87 },
    { "id": 3244, "time": 1626.71 },
    { "id": 3245, "time": 1627.55 },
    { "id": 3246, "time": 1628.42 },
    { "id": 3247, "time": 1629.22 },
    { "id": 3248, "time": 1630.05 },
    { "id": 3249, "time": 1630.94 },
    { "id": 3250, "time": 1631.81 },
    { "id": 3251, "time": 1632.74 },
    { "id": 3252, "time": 1633.7 },
    { "id": 3253, "time": 1634.62 },
    { "id": 3254, "time": 1635.5 },
    { "id": 3255, "time": 1636.42 },
    { "id": 3256, "time": 1637.28 },
    { "id": 3257, "time": 1638.17 },
    { "id": 3258, "time": 1639.05 },
    { "id": 3259, "time": 1639.98 },
    { "id": 3260, "time": 1640.86 },
    { "id": 3261, "time": 1641.85 },
    { "id": 3262, "time": 1642.8 },
    { "id": 3263, "time": 1643.76 },
    { "id": 3264, "time": 1644.67 },
    { "id": 3265, "time": 1645.62 },
    { "id": 3266, "time": 1646.58 },
    { "id": 3267, "time": 1647.52 },
    { "id": 3268, "time": 1648.51 },
    { "id": 3269, "time": 1649.64 },
    { "id": 3270, "time": 1650.38 },
    { "id": 3271, "time": 1651.25 },
    { "id": 3272, "time": 1652.09 },
    { "id": 3273, "time": 1652.96 },
    { "id": 3274, "time": 1653.81 },
    { "id": 3275, "time": 1654.67 },
    { "id": 3276, "time": 1655.56 },
    { "id": 3277, "time": 1656.43 },
    { "id": 3278, "time": 1657.29 },
    { "id": 3279, "time": 1658.16 },
    { "id": 3280, "time": 1659.02 },
    { "id": 3281, "time": 1659.91 },
    { "id": 3282, "time": 1660.78 },
    { "id": 3283, "time": 1661.59 },
    { "id": 3284, "time": 1662.45 },
    { "id": 3285, "time": 1663.3 },
    { "id": 3286, "time": 1664.1 },
    { "id": 3287, "time": 1664.9 },
    { "id": 3288, "time": 1665.82 },
    { "id": 3289, "time": 1666.68 },
    { "id": 3290, "time": 1667.49 },
    { "id": 3291, "time": 1668.31 },
    { "id": 3292, "time": 1669.18 },
    { "id": 3293, "time": 1670.02 },
    { "id": 3294, "time": 1670.85 },
    { "id": 3295, "time": 1671.69 },
    { "id": 3296, "time": 1672.47 },
    { "id": 3297, "time": 1673.32 },
    { "id": 3298, "time": 1674.15 },
    { "id": 3299, "time": 1675.02 },
    { "id": 3300, "time": 1675.84 },
    { "id": 3301, "time": 1676.69 },
    { "id": 3302, "time": 1677.54 },
    { "id": 3303, "time": 1678.37 },
    { "id": 3304, "time": 1679.25 },
    { "id": 3305, "time": 1680.09 },
    { "id": 3306, "time": 1680.95 },
    { "id": 3307, "time": 1681.81 },
    { "id": 3308, "time": 1682.68 },
    { "id": 3309, "time": 1683.53 },
    { "id": 3310, "time": 1684.36 },
    { "id": 3311, "time": 1685.22 },
    { "id": 3312, "time": 1686.07 },
    { "id": 3313, "time": 1686.94 },
    { "id": 3314, "time": 1687.81 },
    { "id": 3315, "time": 1688.63 },
    { "id": 3316, "time": 1689.52 },
    { "id": 3317, "time": 1690.36 },
    { "id": 3318, "time": 1691.23 },
    { "id": 3319, "time": 1692.08 },
    { "id": 3320, "time": 1692.91 },
    { "id": 3321, "time": 1693.76 },
    { "id": 3322, "time": 1694.61 },
    { "id": 3323, "time": 1695.46 },
    { "id": 3324, "time": 1696.36 },
    { "id": 3325, "time": 1697.21 },
    { "id": 3326, "time": 1698.08 },
    { "id": 3327, "time": 1698.89 },
    { "id": 3328, "time": 1699.79 },
    { "id": 3329, "time": 1700.64 },
    { "id": 3330, "time": 1701.49 },
    { "id": 3331, "time": 1702.33 },
    { "id": 3332, "time": 1703.17 },
    { "id": 3333, "time": 1704.01 },
    { "id": 3334, "time": 1704.86 },
    { "id": 3335, "time": 1705.69 },
    { "id": 3336, "time": 1706.56 },
    { "id": 3337, "time": 1707.45 },
    { "id": 3338, "time": 1708.66 },
    { "id": 9904, "time": 1711 }
  ]
}
