{
  "videoId": "VQjPZiACKZM",
  "musicId": "A0009",
  "times": [
    { "id": 9801, "time": 43 },
    { "id": 1, "time": 45.16 },
    { "id": 2, "time": 46.95 },
    { "id": 3, "time": 48.9 },
    { "id": 4, "time": 51.03 },
    { "id": 5, "time": 52.99 },
    { "id": 6, "time": 55.03 },
    { "id": 7, "time": 56.85 },
    { "id": 8, "time": 58.68 },
    { "id": 9, "time": 60.42 },
    { "id": 10, "time": 61.97 },
    { "id": 11, "time": 63.71 },
    { "id": 12, "time": 65.43 },
    { "id": 13, "time": 67.18 },
    { "id": 14, "time": 68.97 },
    { "id": 15, "time": 70.69 },
    { "id": 16, "time": 72.48 },
    { "id": 17, "time": 74.24 },
    { "id": 18, "time": 75.98 },
    { "id": 19, "time": 77.81 },
    { "id": 20, "time": 79.57 },
    { "id": 21, "time": 81.3 },
    { "id": 22, "time": 83.01 },
    { "id": 23, "time": 84.86 },
    { "id": 24, "time": 86.54 },
    { "id": 25, "time": 88.34 },
    { "id": 26, "time": 90.02 },
    { "id": 27, "time": 91.83 },
    { "id": 28, "time": 93.53 },
    { "id": 29, "time": 95.33 },
    { "id": 30, "time": 97.1 },
    { "id": 31, "time": 98.96 },
    { "id": 32, "time": 100.73 },
    { "id": 33, "time": 102.51 },
    { "id": 34, "time": 104.22 },
    { "id": 35, "time": 106.04 },
    { "id": 36, "time": 107.83 },
    { "id": 37, "time": 109.68 },
    { "id": 38, "time": 112.04 },
    { "id": 39, "time": 114.07 },
    { "id": 40, "time": 116.13 },
    { "id": 41, "time": 118.17 },
    { "id": 42, "time": 121.21 },
    { "id": 43, "time": 123.43 },
    { "id": 44, "time": 125.26 },
    { "id": 45, "time": 127.12 },
    { "id": 46, "time": 129.13 },
    { "id": 47, "time": 130.99 },
    { "id": 48, "time": 132.89 },
    { "id": 49, "time": 134.85 },
    { "id": 50, "time": 136.71 },
    { "id": 51, "time": 138.58 },
    { "id": 52, "time": 140.48 },
    { "id": 53, "time": 142.39 },
    { "id": 54, "time": 144.34 },
    { "id": 55, "time": 146.34 },
    { "id": 56, "time": 148.13 },
    { "id": 57, "time": 150.12 },
    { "id": 58, "time": 152.02 },
    { "id": 59, "time": 153.92 },
    { "id": 60, "time": 155.72 },
    { "id": 61, "time": 157.54 },
    { "id": 62, "time": 159.66 },
    { "id": 63, "time": 161.7 },
    { "id": 64, "time": 163.86 },
    { "id": 65, "time": 165.8 },
    { "id": 66, "time": 167.89 },
    { "id": 67, "time": 169.84 },
    { "id": 68, "time": 171.57 },
    { "id": 69, "time": 173.22 },
    { "id": 70, "time": 174.89 },
    { "id": 71, "time": 176.66 },
    { "id": 72, "time": 178.45 },
    { "id": 73, "time": 180.24 },
    { "id": 74, "time": 182 },
    { "id": 75, "time": 183.75 },
    { "id": 76, "time": 185.57 },
    { "id": 77, "time": 187.35 },
    { "id": 78, "time": 189.06 },
    { "id": 79, "time": 190.76 },
    { "id": 80, "time": 192.42 },
    { "id": 81, "time": 194.08 },
    { "id": 82, "time": 195.77 },
    { "id": 83, "time": 197.37 },
    { "id": 84, "time": 199.07 },
    { "id": 85, "time": 200.77 },
    { "id": 86, "time": 202.48 },
    { "id": 87, "time": 204.34 },
    { "id": 88, "time": 206.07 },
    { "id": 89, "time": 207.87 },
    { "id": 90, "time": 209.69 },
    { "id": 91, "time": 211.44 },
    { "id": 92, "time": 213.32 },
    { "id": 93, "time": 215.16 },
    { "id": 94, "time": 216.99 },
    { "id": 95, "time": 218.92 },
    { "id": 96, "time": 220.76 },
    { "id": 97, "time": 222.65 },
    { "id": 98, "time": 224.53 },
    { "id": 99, "time": 226.46 },
    { "id": 100, "time": 228.31 },
    { "id": 101, "time": 230.27 },
    { "id": 102, "time": 232.17 },
    { "id": 103, "time": 234.06 },
    { "id": 104, "time": 236.06 },
    { "id": 105, "time": 237.89 },
    { "id": 106, "time": 239.75 },
    { "id": 107, "time": 241.58 },
    { "id": 108, "time": 243.2 },
    { "id": 109, "time": 245.09 },
    { "id": 110, "time": 247.84 },
    { "id": 2, "time": 249.74 },
    { "id": 3, "time": 251.67 },
    { "id": 4, "time": 253.49 },
    { "id": 5, "time": 255.39 },
    { "id": 6, "time": 257.31 },
    { "id": 7, "time": 259.21 },
    { "id": 8, "time": 261.15 },
    { "id": 9, "time": 262.77 },
    { "id": 10, "time": 264.58 },
    { "id": 11, "time": 266.32 },
    { "id": 12, "time": 268.02 },
    { "id": 13, "time": 269.78 },
    { "id": 14, "time": 271.59 },
    { "id": 15, "time": 273.35 },
    { "id": 16, "time": 275.13 },
    { "id": 17, "time": 276.88 },
    { "id": 18, "time": 278.63 },
    { "id": 19, "time": 280.41 },
    { "id": 20, "time": 282.18 },
    { "id": 21, "time": 283.86 },
    { "id": 22, "time": 285.73 },
    { "id": 23, "time": 287.47 },
    { "id": 24, "time": 289.23 },
    { "id": 25, "time": 290.98 },
    { "id": 26, "time": 292.73 },
    { "id": 27, "time": 294.5 },
    { "id": 28, "time": 296.23 },
    { "id": 29, "time": 297.94 },
    { "id": 30, "time": 299.79 },
    { "id": 31, "time": 301.56 },
    { "id": 32, "time": 303.36 },
    { "id": 33, "time": 305.17 },
    { "id": 34, "time": 306.88 },
    { "id": 35, "time": 308.72 },
    { "id": 36, "time": 310.47 },
    { "id": 37, "time": 312.27 },
    { "id": 38, "time": 314.54 },
    { "id": 39, "time": 316.59 },
    { "id": 40, "time": 318.54 },
    { "id": 41, "time": 320.53 },
    { "id": 42, "time": 323.51 },
    { "id": 43, "time": 325.32 },
    { "id": 44, "time": 327.21 },
    { "id": 45, "time": 329.15 },
    { "id": 46, "time": 331.17 },
    { "id": 47, "time": 333.04 },
    { "id": 48, "time": 334.86 },
    { "id": 49, "time": 336.87 },
    { "id": 50, "time": 338.85 },
    { "id": 51, "time": 340.75 },
    { "id": 52, "time": 342.72 },
    { "id": 53, "time": 344.68 },
    { "id": 54, "time": 346.63 },
    { "id": 55, "time": 348.59 },
    { "id": 56, "time": 350.47 },
    { "id": 57, "time": 352.37 },
    { "id": 58, "time": 354.3 },
    { "id": 59, "time": 356.29 },
    { "id": 60, "time": 358.06 },
    { "id": 61, "time": 360.06 },
    { "id": 62, "time": 361.99 },
    { "id": 63, "time": 364.02 },
    { "id": 64, "time": 366.27 },
    { "id": 65, "time": 368.23 },
    { "id": 66, "time": 370.11 },
    { "id": 67, "time": 371.85 },
    { "id": 68, "time": 373.54 },
    { "id": 69, "time": 375.26 },
    { "id": 70, "time": 376.93 },
    { "id": 71, "time": 378.77 },
    { "id": 72, "time": 380.55 },
    { "id": 73, "time": 382.42 },
    { "id": 74, "time": 384.17 },
    { "id": 75, "time": 385.98 },
    { "id": 76, "time": 387.82 },
    { "id": 77, "time": 389.61 },
    { "id": 78, "time": 391.32 },
    { "id": 79, "time": 392.95 },
    { "id": 80, "time": 394.7 },
    { "id": 81, "time": 396.35 },
    { "id": 82, "time": 398.04 },
    { "id": 83, "time": 399.68 },
    { "id": 84, "time": 401.41 },
    { "id": 85, "time": 403.11 },
    { "id": 86, "time": 404.85 },
    { "id": 87, "time": 406.56 },
    { "id": 88, "time": 408.31 },
    { "id": 89, "time": 410.07 },
    { "id": 90, "time": 411.94 },
    { "id": 91, "time": 413.7 },
    { "id": 92, "time": 415.44 },
    { "id": 93, "time": 417.34 },
    { "id": 94, "time": 419.16 },
    { "id": 95, "time": 421.12 },
    { "id": 96, "time": 422.92 },
    { "id": 97, "time": 424.79 },
    { "id": 98, "time": 426.7 },
    { "id": 99, "time": 428.55 },
    { "id": 100, "time": 430.48 },
    { "id": 101, "time": 432.37 },
    { "id": 102, "time": 434.22 },
    { "id": 103, "time": 436.12 },
    { "id": 104, "time": 438.11 },
    { "id": 105, "time": 439.95 },
    { "id": 106, "time": 441.93 },
    { "id": 107, "time": 443.64 },
    { "id": 108, "time": 445.45 },
    { "id": 109, "time": 447.26 },
    { "id": 111, "time": 449.61 },
    { "id": 112, "time": 451.82 },
    { "id": 113, "time": 453.5 },
    { "id": 114, "time": 455.11 },
    { "id": 115, "time": 457.18 },
    { "id": 116, "time": 459.1 },
    { "id": 117, "time": 460.88 },
    { "id": 118, "time": 462.61 },
    { "id": 119, "time": 464.53 },
    { "id": 120, "time": 466.47 },
    { "id": 121, "time": 468.17 },
    { "id": 122, "time": 470.11 },
    { "id": 123, "time": 472 },
    { "id": 124, "time": 474.3 },
    { "id": 125, "time": 476.12 },
    { "id": 126, "time": 477.96 },
    { "id": 127, "time": 479.86 },
    { "id": 128, "time": 481.64 },
    { "id": 129, "time": 483.41 },
    { "id": 130, "time": 485.33 },
    { "id": 131, "time": 487.22 },
    { "id": 132, "time": 488.92 },
    { "id": 133, "time": 490.89 },
    { "id": 134, "time": 492.73 },
    { "id": 135, "time": 494.51 },
    { "id": 136, "time": 496.35 },
    { "id": 137, "time": 498.12 },
    { "id": 138, "time": 499.96 },
    { "id": 139, "time": 501.62 },
    { "id": 140, "time": 503.34 },
    { "id": 141, "time": 505.04 },
    { "id": 142, "time": 506.68 },
    { "id": 143, "time": 508.27 },
    { "id": 144, "time": 509.95 },
    { "id": 145, "time": 511.56 },
    { "id": 146, "time": 513.18 },
    { "id": 147, "time": 515.24 },
    { "id": 148, "time": 516.96 },
    { "id": 149, "time": 518.63 },
    { "id": 150, "time": 520.32 },
    { "id": 151, "time": 522 },
    { "id": 152, "time": 523.93 },
    { "id": 153, "time": 525.78 },
    { "id": 154, "time": 527.59 },
    { "id": 155, "time": 529.53 },
    { "id": 156, "time": 531.35 },
    { "id": 157, "time": 532.96 },
    { "id": 158, "time": 534.63 },
    { "id": 159, "time": 536.36 },
    { "id": 160, "time": 538.22 },
    { "id": 161, "time": 539.96 },
    { "id": 162, "time": 541.78 },
    { "id": 163, "time": 543.66 },
    { "id": 164, "time": 545.45 },
    { "id": 165, "time": 547.11 },
    { "id": 166, "time": 548.78 },
    { "id": 167, "time": 550.5 },
    { "id": 168, "time": 552.41 },
    { "id": 169, "time": 554.14 },
    { "id": 170, "time": 556.03 },
    { "id": 171, "time": 557.93 },
    { "id": 172, "time": 559.65 },
    { "id": 173, "time": 561.36 },
    { "id": 174, "time": 562.99 },
    { "id": 175, "time": 564.62 },
    { "id": 176, "time": 566.27 },
    { "id": 177, "time": 568.08 },
    { "id": 178, "time": 569.67 },
    { "id": 179, "time": 571.27 },
    { "id": 180, "time": 572.92 },
    { "id": 181, "time": 574.66 },
    { "id": 182, "time": 576.28 },
    { "id": 183, "time": 577.93 },
    { "id": 184, "time": 579.52 },
    { "id": 185, "time": 581.27 },
    { "id": 186, "time": 582.99 },
    { "id": 187, "time": 584.6 },
    { "id": 188, "time": 586.29 },
    { "id": 189, "time": 587.91 },
    { "id": 190, "time": 589.63 },
    { "id": 191, "time": 591.25 },
    { "id": 192, "time": 592.81 },
    { "id": 193, "time": 594.45 },
    { "id": 194, "time": 596.15 },
    { "id": 195, "time": 597.81 },
    { "id": 196, "time": 599.49 },
    { "id": 197, "time": 601.17 },
    { "id": 198, "time": 602.93 },
    { "id": 199, "time": 604.91 },
    { "id": 200, "time": 606.75 },
    { "id": 201, "time": 608.45 },
    { "id": 202, "time": 610.15 },
    { "id": 203, "time": 611.88 },
    { "id": 204, "time": 613.59 },
    { "id": 205, "time": 615.29 },
    { "id": 206, "time": 617.14 },
    { "id": 207, "time": 619 },
    { "id": 208, "time": 620.81 },
    { "id": 209, "time": 622.55 },
    { "id": 210, "time": 624.36 },
    { "id": 211, "time": 626.16 },
    { "id": 212, "time": 627.96 },
    { "id": 213, "time": 629.56 },
    { "id": 214, "time": 631.26 },
    { "id": 215, "time": 632.98 },
    { "id": 216, "time": 634.7 },
    { "id": 217, "time": 636.43 },
    { "id": 218, "time": 638.26 },
    { "id": 219, "time": 640.07 },
    { "id": 220, "time": 641.84 },
    { "id": 221, "time": 643.58 },
    { "id": 222, "time": 645.22 },
    { "id": 223, "time": 646.92 },
    { "id": 224, "time": 648.68 },
    { "id": 225, "time": 650.47 },
    { "id": 226, "time": 652.23 },
    { "id": 227, "time": 653.99 },
    { "id": 228, "time": 655.71 },
    { "id": 229, "time": 657.36 },
    { "id": 230, "time": 659.16 },
    { "id": 231, "time": 660.93 },
    { "id": 232, "time": 662.71 },
    { "id": 233, "time": 664.44 },
    { "id": 234, "time": 666.24 },
    { "id": 235, "time": 667.92 },
    { "id": 236, "time": 669.67 },
    { "id": 237, "time": 671.37 },
    { "id": 238, "time": 673.1 },
    { "id": 239, "time": 674.77 },
    { "id": 240, "time": 676.55 },
    { "id": 241, "time": 678.29 },
    { "id": 242, "time": 680.07 },
    { "id": 243, "time": 681.84 },
    { "id": 244, "time": 683.61 },
    { "id": 245, "time": 685.32 },
    { "id": 246, "time": 687.04 },
    { "id": 247, "time": 688.83 },
    { "id": 248, "time": 690.55 },
    { "id": 249, "time": 692.27 },
    { "id": 250, "time": 694.02 },
    { "id": 251, "time": 695.76 },
    { "id": 252, "time": 697.65 },
    { "id": 253, "time": 699.71 },
    { "id": 254, "time": 701.79 },
    { "id": 255, "time": 703.42 },
    { "id": 256, "time": 705.33 },
    { "id": 257, "time": 708.81 },
    { "id": 258, "time": 710.74 },
    { "id": 259, "time": 712.71 },
    { "id": 260, "time": 714.75 },
    { "id": 261, "time": 716.64 },
    { "id": 262, "time": 718.44 },
    { "id": 263, "time": 720.26 },
    { "id": 264, "time": 722.35 },
    { "id": 265, "time": 724.25 },
    { "id": 266, "time": 726.08 },
    { "id": 267, "time": 728.08 },
    { "id": 268, "time": 729.98 },
    { "id": 269, "time": 731.79 },
    { "id": 270, "time": 733.84 },
    { "id": 271, "time": 735.64 },
    { "id": 272, "time": 737.51 },
    { "id": 273, "time": 739.57 },
    { "id": 274, "time": 741.5 },
    { "id": 275, "time": 743.3 },
    { "id": 276, "time": 745.18 },
    { "id": 277, "time": 747.12 },
    { "id": 278, "time": 749.15 },
    { "id": 279, "time": 751.03 },
    { "id": 280, "time": 752.97 },
    { "id": 281, "time": 755.07 },
    { "id": 282, "time": 756.94 },
    { "id": 283, "time": 759.05 },
    { "id": 284, "time": 761.11 },
    { "id": 285, "time": 763.07 },
    { "id": 286, "time": 764.82 },
    { "id": 287, "time": 766.51 },
    { "id": 288, "time": 768.12 },
    { "id": 289, "time": 769.87 },
    { "id": 290, "time": 771.69 },
    { "id": 291, "time": 773.47 },
    { "id": 292, "time": 775.27 },
    { "id": 293, "time": 777.03 },
    { "id": 294, "time": 778.79 },
    { "id": 295, "time": 780.52 },
    { "id": 296, "time": 782.27 },
    { "id": 297, "time": 783.98 },
    { "id": 298, "time": 785.67 },
    { "id": 299, "time": 787.41 },
    { "id": 300, "time": 789.04 },
    { "id": 301, "time": 790.66 },
    { "id": 302, "time": 792.32 },
    { "id": 303, "time": 793.93 },
    { "id": 304, "time": 795.72 },
    { "id": 305, "time": 797.29 },
    { "id": 306, "time": 799.11 },
    { "id": 307, "time": 800.84 },
    { "id": 308, "time": 802.71 },
    { "id": 309, "time": 804.49 },
    { "id": 310, "time": 806.22 },
    { "id": 311, "time": 808.04 },
    { "id": 312, "time": 809.93 },
    { "id": 313, "time": 811.66 },
    { "id": 314, "time": 813.68 },
    { "id": 315, "time": 815.46 },
    { "id": 316, "time": 817.28 },
    { "id": 317, "time": 819.19 },
    { "id": 318, "time": 821.03 },
    { "id": 319, "time": 822.92 },
    { "id": 320, "time": 824.77 },
    { "id": 321, "time": 826.57 },
    { "id": 322, "time": 828.4 },
    { "id": 323, "time": 830.2 },
    { "id": 324, "time": 832.1 },
    { "id": 325, "time": 834.1 },
    { "id": 326, "time": 835.94 },
    { "id": 327, "time": 837.66 },
    { "id": 328, "time": 839.43 },
    { "id": 329, "time": 841.91 },
    { "id": 330, "time": 843.96 },
    { "id": 331, "time": 845.74 },
    { "id": 332, "time": 847.53 },
    { "id": 333, "time": 849.43 },
    { "id": 334, "time": 851.37 },
    { "id": 335, "time": 853.46 },
    { "id": 336, "time": 855.22 },
    { "id": 337, "time": 857.19 },
    { "id": 338, "time": 859.15 },
    { "id": 339, "time": 861.22 },
    { "id": 340, "time": 863.04 },
    { "id": 341, "time": 864.84 },
    { "id": 342, "time": 866.75 },
    { "id": 343, "time": 868.86 },
    { "id": 344, "time": 870.73 },
    { "id": 345, "time": 872.58 },
    { "id": 346, "time": 874.38 },
    { "id": 347, "time": 876.08 },
    { "id": 348, "time": 877.56 },
    { "id": 349, "time": 879.3 },
    { "id": 350, "time": 880.98 },
    { "id": 351, "time": 882.73 },
    { "id": 352, "time": 884.49 },
    { "id": 353, "time": 886.3 },
    { "id": 354, "time": 888.11 },
    { "id": 355, "time": 889.87 },
    { "id": 356, "time": 891.73 },
    { "id": 357, "time": 893.67 },
    { "id": 358, "time": 895.56 },
    { "id": 359, "time": 897.24 },
    { "id": 360, "time": 899.19 },
    { "id": 361, "time": 901.49 },
    { "id": 362, "time": 903.29 },
    { "id": 363, "time": 905.26 },
    { "id": 364, "time": 907.32 },
    { "id": 365, "time": 909.49 },
    { "id": 366, "time": 911.24 },
    { "id": 367, "time": 913.1 },
    { "id": 368, "time": 915.22 },
    { "id": 369, "time": 917.92 },
    { "id": 9901, "time": 922 },
    { "id": 9802, "time": 936 },
    { "id": 1001, "time": 938.92 },
    { "id": 1002, "time": 941.1 },
    { "id": 1003, "time": 943.42 },
    { "id": 1004, "time": 945.54 },
    { "id": 1005, "time": 947.77 },
    { "id": 1006, "time": 949.75 },
    { "id": 1007, "time": 951.96 },
    { "id": 1008, "time": 954.03 },
    { "id": 1009, "time": 956.27 },
    { "id": 1010, "time": 958.3 },
    { "id": 1011, "time": 960.46 },
    { "id": 1012, "time": 962.53 },
    { "id": 1013, "time": 964.66 },
    { "id": 1014, "time": 966.68 },
    { "id": 1015, "time": 968.79 },
    { "id": 1016, "time": 970.94 },
    { "id": 1017, "time": 973 },
    { "id": 1018, "time": 975.09 },
    { "id": 1019, "time": 977.08 },
    { "id": 1020, "time": 979.12 },
    { "id": 1021, "time": 981.16 },
    { "id": 1022, "time": 983.41 },
    { "id": 1023, "time": 985.37 },
    { "id": 1024, "time": 987.34 },
    { "id": 1025, "time": 989.43 },
    { "id": 1026, "time": 991.44 },
    { "id": 1027, "time": 993.44 },
    { "id": 1028, "time": 995.62 },
    { "id": 1029, "time": 997.84 },
    { "id": 1030, "time": 999.78 },
    { "id": 1031, "time": 1001.81 },
    { "id": 1032, "time": 1003.83 },
    { "id": 1033, "time": 1005.89 },
    { "id": 1034, "time": 1007.81 },
    { "id": 1035, "time": 1009.79 },
    { "id": 1036, "time": 1011.8 },
    { "id": 1037, "time": 1013.88 },
    { "id": 1038, "time": 1015.86 },
    { "id": 1039, "time": 1017.85 },
    { "id": 1040, "time": 1019.8 },
    { "id": 1041, "time": 1021.82 },
    { "id": 1042, "time": 1023.78 },
    { "id": 1043, "time": 1025.69 },
    { "id": 1044, "time": 1027.64 },
    { "id": 1045, "time": 1029.66 },
    { "id": 1046, "time": 1031.71 },
    { "id": 1047, "time": 1033.73 },
    { "id": 1048, "time": 1035.65 },
    { "id": 1049, "time": 1037.6 },
    { "id": 1050, "time": 1039.7 },
    { "id": 1051, "time": 1041.79 },
    { "id": 1052, "time": 1043.82 },
    { "id": 1053, "time": 1045.85 },
    { "id": 1054, "time": 1047.91 },
    { "id": 1055, "time": 1049.9 },
    { "id": 1056, "time": 1051.89 },
    { "id": 1057, "time": 1053.97 },
    { "id": 1058, "time": 1055.97 },
    { "id": 1059, "time": 1058.01 },
    { "id": 1060, "time": 1060.08 },
    { "id": 1061, "time": 1062.07 },
    { "id": 1062, "time": 1064.12 },
    { "id": 1063, "time": 1066.25 },
    { "id": 1064, "time": 1068.14 },
    { "id": 1065, "time": 1070.15 },
    { "id": 1066, "time": 1072.08 },
    { "id": 1067, "time": 1073.99 },
    { "id": 1068, "time": 1075.97 },
    { "id": 1069, "time": 1077.9 },
    { "id": 1070, "time": 1079.98 },
    { "id": 1071, "time": 1081.92 },
    { "id": 1072, "time": 1083.88 },
    { "id": 1073, "time": 1085.87 },
    { "id": 1074, "time": 1087.94 },
    { "id": 1075, "time": 1090.08 },
    { "id": 1076, "time": 1092.14 },
    { "id": 1077, "time": 1094.16 },
    { "id": 1078, "time": 1096.12 },
    { "id": 1079, "time": 1098.19 },
    { "id": 1080, "time": 1100.22 },
    { "id": 1081, "time": 1102.33 },
    { "id": 1082, "time": 1104.42 },
    { "id": 1083, "time": 1106.51 },
    { "id": 1084, "time": 1108.6 },
    { "id": 1085, "time": 1110.61 },
    { "id": 1086, "time": 1112.73 },
    { "id": 1087, "time": 1114.76 },
    { "id": 1088, "time": 1116.8 },
    { "id": 1089, "time": 1118.89 },
    { "id": 1090, "time": 1120.85 },
    { "id": 1091, "time": 1122.8 },
    { "id": 1092, "time": 1124.74 },
    { "id": 1093, "time": 1126.63 },
    { "id": 1094, "time": 1128.6 },
    { "id": 1095, "time": 1130.62 },
    { "id": 1096, "time": 1132.55 },
    { "id": 1097, "time": 1134.45 },
    { "id": 1098, "time": 1136.44 },
    { "id": 1099, "time": 1138.36 },
    { "id": 1100, "time": 1140.4 },
    { "id": 1101, "time": 1142.26 },
    { "id": 1102, "time": 1144.39 },
    { "id": 1103, "time": 1146.4 },
    { "id": 1104, "time": 1148.5 },
    { "id": 1105, "time": 1150.61 },
    { "id": 1106, "time": 1152.71 },
    { "id": 1107, "time": 1154.73 },
    { "id": 1108, "time": 1156.75 },
    { "id": 1109, "time": 1158.74 },
    { "id": 1110, "time": 1160.78 },
    { "id": 1111, "time": 1162.9 },
    { "id": 1112, "time": 1164.96 },
    { "id": 1113, "time": 1166.92 },
    { "id": 1114, "time": 1168.99 },
    { "id": 1115, "time": 1171.01 },
    { "id": 1116, "time": 1173.06 },
    { "id": 1117, "time": 1175.11 },
    { "id": 1118, "time": 1177.13 },
    { "id": 1119, "time": 1179.17 },
    { "id": 1120, "time": 1181.14 },
    { "id": 1121, "time": 1183.34 },
    { "id": 1122, "time": 1185.44 },
    { "id": 1123, "time": 1187.53 },
    { "id": 1124, "time": 1189.43 },
    { "id": 1125, "time": 1191.56 },
    { "id": 1126, "time": 1193.59 },
    { "id": 1127, "time": 1195.7 },
    { "id": 1128, "time": 1197.71 },
    { "id": 1129, "time": 1199.98 },
    { "id": 1130, "time": 1202.07 },
    { "id": 1131, "time": 1204.11 },
    { "id": 1132, "time": 1206.25 },
    { "id": 1133, "time": 1208.31 },
    { "id": 1134, "time": 1210.41 },
    { "id": 1135, "time": 1212.46 },
    { "id": 1136, "time": 1214.58 },
    { "id": 1137, "time": 1216.49 },
    { "id": 1138, "time": 1218.55 },
    { "id": 1139, "time": 1220.71 },
    { "id": 1140, "time": 1222.86 },
    { "id": 1141, "time": 1225.11 },
    { "id": 1142, "time": 1227.97 },
    { "id": 1143, "time": 1230.41 },
    { "id": 1144, "time": 1232.49 },
    { "id": 1145, "time": 1234.74 },
    { "id": 1146, "time": 1237.02 },
    { "id": 1147, "time": 1239.01 },
    { "id": 1148, "time": 1241.18 },
    { "id": 1149, "time": 1243.31 },
    { "id": 1150, "time": 1245.43 },
    { "id": 1151, "time": 1247.58 },
    { "id": 1152, "time": 1249.68 },
    { "id": 1153, "time": 1251.66 },
    { "id": 1154, "time": 1253.79 },
    { "id": 1155, "time": 1255.93 },
    { "id": 1156, "time": 1257.99 },
    { "id": 1157, "time": 1260.21 },
    { "id": 1158, "time": 1262.22 },
    { "id": 1159, "time": 1264.21 },
    { "id": 1160, "time": 1266.15 },
    { "id": 1161, "time": 1268.22 },
    { "id": 1162, "time": 1270.27 },
    { "id": 1163, "time": 1272.46 },
    { "id": 1164, "time": 1274.44 },
    { "id": 1165, "time": 1276.43 },
    { "id": 1166, "time": 1278.49 },
    { "id": 1167, "time": 1280.49 },
    { "id": 1168, "time": 1282.58 },
    { "id": 1169, "time": 1284.85 },
    { "id": 1170, "time": 1286.79 },
    { "id": 1171, "time": 1288.88 },
    { "id": 1172, "time": 1290.94 },
    { "id": 1173, "time": 1293.03 },
    { "id": 1174, "time": 1295.08 },
    { "id": 1175, "time": 1297 },
    { "id": 1176, "time": 1299.1 },
    { "id": 1177, "time": 1301.13 },
    { "id": 1178, "time": 1303.14 },
    { "id": 1179, "time": 1305.09 },
    { "id": 1180, "time": 1307.06 },
    { "id": 1181, "time": 1309.09 },
    { "id": 1182, "time": 1311.15 },
    { "id": 1183, "time": 1313.12 },
    { "id": 1184, "time": 1315.16 },
    { "id": 1185, "time": 1317.07 },
    { "id": 1186, "time": 1319.33 },
    { "id": 1187, "time": 1321.37 },
    { "id": 1188, "time": 1323.28 },
    { "id": 1189, "time": 1325.21 },
    { "id": 1190, "time": 1327.2 },
    { "id": 1191, "time": 1329.24 },
    { "id": 1192, "time": 1331.39 },
    { "id": 1193, "time": 1333.46 },
    { "id": 1194, "time": 1335.53 },
    { "id": 1195, "time": 1337.56 },
    { "id": 1196, "time": 1339.55 },
    { "id": 1197, "time": 1341.57 },
    { "id": 1198, "time": 1343.59 },
    { "id": 1199, "time": 1345.55 },
    { "id": 1200, "time": 1347.56 },
    { "id": 1201, "time": 1349.59 },
    { "id": 1202, "time": 1351.58 },
    { "id": 1203, "time": 1353.7 },
    { "id": 1204, "time": 1355.66 },
    { "id": 1205, "time": 1357.62 },
    { "id": 1206, "time": 1359.59 },
    { "id": 1207, "time": 1361.59 },
    { "id": 1208, "time": 1363.57 },
    { "id": 1209, "time": 1365.65 },
    { "id": 1210, "time": 1367.67 },
    { "id": 1211, "time": 1369.81 },
    { "id": 1212, "time": 1371.85 },
    { "id": 1213, "time": 1373.92 },
    { "id": 1214, "time": 1376.14 },
    { "id": 1215, "time": 1378.31 },
    { "id": 1216, "time": 1380.5 },
    { "id": 1217, "time": 1382.52 },
    { "id": 1218, "time": 1384.63 },
    { "id": 1219, "time": 1386.82 },
    { "id": 1220, "time": 1388.98 },
    { "id": 1221, "time": 1391.07 },
    { "id": 1222, "time": 1393.23 },
    { "id": 1223, "time": 1395.4 },
    { "id": 1224, "time": 1397.53 },
    { "id": 1225, "time": 1399.68 },
    { "id": 1226, "time": 1401.76 },
    { "id": 1227, "time": 1403.95 },
    { "id": 1228, "time": 1406 },
    { "id": 1229, "time": 1408.17 },
    { "id": 1230, "time": 1410.22 },
    { "id": 1231, "time": 1412.23 },
    { "id": 1232, "time": 1414.37 },
    { "id": 1233, "time": 1416.4 },
    { "id": 1234, "time": 1418.36 },
    { "id": 1235, "time": 1420.34 },
    { "id": 1236, "time": 1422.36 },
    { "id": 1237, "time": 1424.37 },
    { "id": 1238, "time": 1426.37 },
    { "id": 1239, "time": 1428.36 },
    { "id": 1240, "time": 1430.41 },
    { "id": 1241, "time": 1432.56 },
    { "id": 1242, "time": 1434.59 },
    { "id": 1243, "time": 1436.72 },
    { "id": 1244, "time": 1438.77 },
    { "id": 1245, "time": 1440.96 },
    { "id": 1246, "time": 1443.04 },
    { "id": 1247, "time": 1445.16 },
    { "id": 1248, "time": 1447.22 },
    { "id": 1249, "time": 1449.28 },
    { "id": 1250, "time": 1451.35 },
    { "id": 1251, "time": 1453.32 },
    { "id": 1252, "time": 1455.46 },
    { "id": 1253, "time": 1457.64 },
    { "id": 1254, "time": 1459.86 },
    { "id": 1255, "time": 1461.94 },
    { "id": 1256, "time": 1464.14 },
    { "id": 1257, "time": 1466.23 },
    { "id": 1258, "time": 1468.71 },
    { "id": 1259, "time": 1470.75 },
    { "id": 1260, "time": 1472.91 },
    { "id": 1261, "time": 1475.07 },
    { "id": 1262, "time": 1477.2 },
    { "id": 1263, "time": 1479.3 },
    { "id": 1264, "time": 1481.3 },
    { "id": 1265, "time": 1483.43 },
    { "id": 1266, "time": 1485.52 },
    { "id": 1267, "time": 1487.66 },
    { "id": 1268, "time": 1490.2 },
    { "id": 1269, "time": 1492.19 },
    { "id": 1270, "time": 1494.38 },
    { "id": 1271, "time": 1496.37 },
    { "id": 1272, "time": 1498.54 },
    { "id": 1273, "time": 1500.71 },
    { "id": 1274, "time": 1502.89 },
    { "id": 1275, "time": 1505.02 },
    { "id": 1276, "time": 1507.11 },
    { "id": 1277, "time": 1509.22 },
    { "id": 1278, "time": 1511.42 },
    { "id": 1279, "time": 1513.59 },
    { "id": 1280, "time": 1516 },
    { "id": 1281, "time": 1518.15 },
    { "id": 1282, "time": 1520.25 },
    { "id": 1283, "time": 1522.32 },
    { "id": 1284, "time": 1524.33 },
    { "id": 1285, "time": 1526.39 },
    { "id": 1286, "time": 1529.16 },
    { "id": 1287, "time": 1531.14 },
    { "id": 1288, "time": 1533.3 },
    { "id": 1289, "time": 1535.57 },
    { "id": 1290, "time": 1538.02 },
    { "id": 1291, "time": 1540.05 },
    { "id": 1292, "time": 1542.16 },
    { "id": 1293, "time": 1544.17 },
    { "id": 1294, "time": 1546.23 },
    { "id": 1295, "time": 1548.39 },
    { "id": 1296, "time": 1550.85 },
    { "id": 1297, "time": 1553.19 },
    { "id": 1298, "time": 1555.29 },
    { "id": 1299, "time": 1557.75 },
    { "id": 1300, "time": 1559.99 },
    { "id": 1301, "time": 1562.47 },
    { "id": 1302, "time": 1564.73 },
    { "id": 1303, "time": 1567.08 },
    { "id": 1304, "time": 1569.38 },
    { "id": 1305, "time": 1571.82 },
    { "id": 1306, "time": 1574.02 },
    { "id": 1307, "time": 1576.31 },
    { "id": 1308, "time": 1578.69 },
    { "id": 1309, "time": 1581.05 },
    { "id": 1310, "time": 1583.14 },
    { "id": 1311, "time": 1585.39 },
    { "id": 1312, "time": 1588.05 },
    { "id": 9902, "time": 1600 }
  ]
}
