{
  "scoreId": "312394",
  "musicId": "A0016",
  "isFirstEndingOmitted": true,
  "positions": [
    {
      "page": 1,
      "rows": [
        {
          "id": 1,
          "top": 179,
          "height": 279,
          "blocks": [
            { "id": 1, "width": 51, "left": 98 },
            { "id": 2, "width": 31, "left": 0 },
            { "id": 3, "width": 30, "left": 0 },
            { "id": 4, "width": 18, "left": 0 },
            { "id": 5, "width": 27, "left": 0 },
            { "id": 6, "width": 30, "left": 0 },
            { "id": 7, "width": 28, "left": 0 },
            { "id": 8, "width": 30, "left": 0 },
            { "id": 9, "width": 22, "left": 0 },
            { "id": 10, "width": 22, "left": 0 },
            { "id": 11, "width": 23, "left": 0 },
            { "id": 12, "width": 31, "left": 0 },
            { "id": 13, "width": 23, "left": 0 }
          ]
        }
      ]
    },
    {
      "page": 2,
      "rows": [
        {
          "id": 2,
          "top": 19,
          "height": 213,
          "blocks": [
            { "id": 14, "width": 40, "left": 38 },
            { "id": 15, "width": 28, "left": 0 },
            { "id": 16, "width": 33, "left": 0 },
            { "id": 17, "width": 37, "left": 0 },
            { "id": 18, "width": 36, "left": 0 },
            { "id": 19, "width": 38, "left": 0 },
            { "id": 20, "width": 37, "left": 0 },
            { "id": 21, "width": 37, "left": 0 },
            { "id": 22, "width": 38, "left": 0 },
            { "id": 23, "width": 36, "left": 0 },
            { "id": 24, "width": 37, "left": 0 },
            { "id": 25, "width": 36, "left": 0 }
          ]
        },
        {
          "id": 3,
          "top": 252,
          "height": 224,
          "blocks": [
            { "id": 26, "width": 56, "left": 36 },
            { "id": 27, "width": 33, "left": 0 },
            { "id": 28, "width": 32, "left": 0 },
            { "id": 29, "width": 29, "left": 0 },
            { "id": 30, "width": 32, "left": 0 },
            { "id": 31, "width": 33, "left": 0 },
            { "id": 32, "width": 32, "left": 0 },
            { "id": 33, "width": 36, "left": 0 },
            { "id": 34, "width": 36, "left": 0 },
            { "id": 35, "width": 37, "left": 0 },
            { "id": 36, "width": 37, "left": 0 },
            { "id": 37, "width": 40, "left": 0 }
          ]
        }
      ]
    },
    {
      "page": 3,
      "rows": [
        {
          "id": 4,
          "top": 22,
          "height": 218,
          "blocks": [
            { "id": 38, "width": 52, "left": 39 },
            { "id": 39, "width": 34, "left": 0 },
            { "id": 40, "width": 34, "left": 0 },
            { "id": 41, "width": 30, "left": 0 },
            { "id": 42, "width": 46, "left": 0 },
            { "id": 43, "width": 35, "left": 0 },
            { "id": 44, "width": 35, "left": 0 },
            { "id": 45, "width": 31, "left": 0 },
            { "id": 46, "width": 53, "left": 0 },
            { "id": 47, "width": 37, "left": 0 },
            { "id": 48, "width": 40, "left": 0 }
          ]
        },
        {
          "id": 5,
          "top": 260,
          "height": 210,
          "blocks": [
            { "id": 49, "width": 56, "left": 38 },
            { "id": 50, "width": 38, "left": 0 },
            { "id": 51, "width": 46, "left": 0 },
            { "id": 52, "width": 45, "left": 0 },
            { "id": 53, "width": 41, "left": 0 },
            { "id": 54, "width": 29, "left": 0 },
            { "id": 55, "width": 30, "left": 0 },
            { "id": 56, "width": 29, "left": 0 },
            { "id": 57, "width": 25, "left": 0 },
            { "id": 58, "width": 30, "left": 0 },
            { "id": 59, "width": 30, "left": 0 },
            { "id": 60, "width": 29, "left": 0 }
          ]
        }
      ]
    },
    {
      "page": 4,
      "rows": [
        {
          "id": 6,
          "top": 18,
          "height": 215,
          "blocks": [
            { "id": 61, "width": 46, "left": 38 },
            { "id": 62, "width": 31, "left": 0 },
            { "id": 63, "width": 24, "left": 0 },
            { "id": 64, "width": 33, "left": 0 },
            { "id": 65, "width": 36, "left": 0 },
            { "id": 66, "width": 34, "left": 0 },
            { "id": 67, "width": 35, "left": 0 },
            { "id": 68, "width": 35, "left": 0 },
            { "id": 69, "width": 30, "left": 0 },
            { "id": 70, "width": 32, "left": 0 },
            { "id": 71, "width": 32, "left": 0 },
            { "id": 72, "width": 32, "left": 0 },
            { "id": 73, "width": 34, "left": 0 }
          ]
        },
        {
          "id": 7,
          "top": 255,
          "height": 216,
          "blocks": [
            { "id": 74, "width": 50, "left": 33 },
            { "id": 75, "width": 34, "left": 0 },
            { "id": 76, "width": 35, "left": 0 },
            { "id": 77, "width": 31, "left": 0 },
            { "id": 78, "width": 30, "left": 0 },
            { "id": 79, "width": 31, "left": 0 },
            { "id": 80, "width": 32, "left": 0 },
            { "id": 81, "width": 30, "left": 0 },
            { "id": 82, "width": 31, "left": 0 },
            { "id": 83, "width": 44, "left": 0 },
            { "id": 84, "width": 44, "left": 0 },
            { "id": 85, "width": 43, "left": 0 }
          ]
        }
      ]
    },
    {
      "page": 5,
      "rows": [
        {
          "id": 8,
          "top": 29,
          "height": 216,
          "blocks": [
            { "id": 86, "width": 58, "left": 41 },
            { "id": 87, "width": 32, "left": 0 },
            { "id": 88, "width": 34, "left": 0 },
            { "id": 89, "width": 34, "left": 0 },
            { "id": 90, "width": 33, "left": 0 },
            { "id": 91, "width": 34, "left": 0 },
            { "id": 92, "width": 34, "left": 0 },
            { "id": 93, "width": 41, "left": 0 },
            { "id": 94, "width": 47, "left": 0 },
            { "id": 95, "width": 48, "left": 0 },
            { "id": 96, "width": 32, "left": 0 }
          ]
        },
        {
          "id": 9,
          "top": 266,
          "height": 209,
          "blocks": [
            { "id": 97, "width": 47, "left": 38 },
            { "id": 98, "width": 30, "left": 0 },
            { "id": 99, "width": 37, "left": 0 },
            { "id": 100, "width": 36, "left": 0 },
            { "id": 101, "width": 41, "left": 0 },
            { "id": 102, "width": 40, "left": 0 },
            { "id": 103, "width": 27, "left": 0 },
            { "id": 104, "width": 31, "left": 0 },
            { "id": 105, "width": 31, "left": 0 },
            { "id": 106, "width": 39, "left": 0 },
            { "id": 107, "width": 32, "left": 0 },
            { "id": 108, "width": 36, "left": 0 }
          ]
        }
      ]
    },
    {
      "page": 6,
      "rows": [
        {
          "id": 10,
          "top": 22,
          "height": 221,
          "blocks": [
            { "id": 109, "width": 50, "left": 37 },
            { "id": 110, "width": 37, "left": 0 },
            { "id": 111, "width": 38, "left": 0 },
            { "id": 112, "width": 40, "left": 0 },
            { "id": 113, "width": 38, "left": 0 },
            { "id": 114, "width": 38, "left": 0 },
            { "id": 115, "width": 39, "left": 0 },
            { "id": 116, "width": 39, "left": 0 },
            { "id": 117, "width": 37, "left": 0 },
            { "id": 118, "width": 39, "left": 0 },
            { "id": 119, "width": 38, "left": 0 }
          ]
        },
        {
          "id": 11,
          "top": 259,
          "height": 216,
          "blocks": [
            { "id": 120, "width": 56, "left": 34 },
            { "id": 121, "width": 36, "left": 0 },
            { "id": 122, "width": 38, "left": 0 },
            { "id": 123, "width": 38, "left": 0 },
            { "id": 124, "width": 39, "left": 0 },
            { "id": 125, "width": 37, "left": 0 },
            { "id": 126, "width": 38, "left": 0 },
            { "id": 127, "width": 38, "left": 0 },
            { "id": 128, "width": 39, "left": 0 },
            { "id": 129, "width": 38, "left": 0 },
            { "id": 130, "width": 38, "left": 0 }
          ]
        }
      ]
    },
    {
      "page": 7,
      "rows": [
        {
          "id": 12,
          "top": 20,
          "height": 208,
          "blocks": [
            { "id": 131, "width": 57, "left": 39 },
            { "id": 132, "width": 36, "left": 0 },
            { "id": 133, "width": 37, "left": 0 },
            { "id": 134, "width": 38, "left": 0 },
            { "id": 135, "width": 31, "left": 0 },
            { "id": 136, "width": 30, "left": 0 },
            { "id": 137, "width": 31, "left": 0 },
            { "id": 138, "width": 33, "left": 0 },
            { "id": 139, "width": 32, "left": 0 },
            { "id": 140, "width": 36, "left": 0 },
            { "id": 141, "width": 31, "left": 0 },
            { "id": 142, "width": 37, "left": 0 }
          ]
        },
        {
          "id": 13,
          "top": 254,
          "height": 218,
          "blocks": [
            { "id": 143, "width": 48, "left": 37 },
            { "id": 144, "width": 29, "left": 0 },
            { "id": 145, "width": 29, "left": 0 },
            { "id": 146, "width": 31, "left": 0 },
            { "id": 147, "width": 31, "left": 0 },
            { "id": 148, "width": 33, "left": 0 },
            { "id": 149, "width": 32, "left": 0 },
            { "id": 150, "width": 34, "left": 0 },
            { "id": 151, "width": 40, "left": 0 },
            { "id": 152, "width": 40, "left": 0 },
            { "id": 153, "width": 40, "left": 0 },
            { "id": 154, "width": 42, "left": 0 }
          ]
        }
      ]
    },
    {
      "page": 8,
      "rows": [
        {
          "id": 14,
          "top": 21,
          "height": 217,
          "blocks": [
            { "id": 155, "width": 63, "left": 36 },
            { "id": 156, "width": 43, "left": 0 },
            { "id": 157, "width": 44, "left": 0 },
            { "id": 158, "width": 43, "left": 0 },
            { "id": 159, "width": 40, "left": 0 },
            { "id": 160, "width": 41, "left": 0 },
            { "id": 161, "width": 39, "left": 0 },
            { "id": 162, "width": 41, "left": 0 },
            { "id": 163, "width": 41, "left": 0 },
            { "id": 164, "width": 42, "left": 0 }
          ]
        },
        {
          "id": 15,
          "top": 258,
          "height": 219,
          "blocks": [
            { "id": 165, "width": 59, "left": 32 },
            { "id": 166, "width": 40, "left": 0 },
            { "id": 167, "width": 42, "left": 0 },
            { "id": 168, "width": 43, "left": 0 },
            { "id": 169, "width": 42, "left": 0 },
            { "id": 170, "width": 42, "left": 0 },
            { "id": 171, "width": 42, "left": 0 },
            { "id": 172, "width": 42, "left": 0 },
            { "id": 173, "width": 43, "left": 0 },
            { "id": 174, "width": 43, "left": 0 }
          ]
        }
      ]
    },
    {
      "page": 9,
      "rows": [
        {
          "id": 16,
          "top": 23,
          "height": 212,
          "blocks": [
            { "id": 175, "width": 56, "left": 40 },
            { "id": 176, "width": 39, "left": 0 },
            { "id": 177, "width": 36, "left": 0 },
            { "id": 178, "width": 38, "left": 0 },
            { "id": 179, "width": 37, "left": 0 },
            { "id": 180, "width": 37, "left": 0 },
            { "id": 181, "width": 38, "left": 0 },
            { "id": 182, "width": 37, "left": 0 },
            { "id": 183, "width": 38, "left": 0 },
            { "id": 184, "width": 37, "left": 0 },
            { "id": 185, "width": 36, "left": 0 }
          ]
        },
        {
          "id": 17,
          "top": 251,
          "height": 219,
          "blocks": [
            { "id": 186, "width": 55, "left": 37 },
            { "id": 187, "width": 28, "left": 0 },
            { "id": 188, "width": 29, "left": 0 },
            { "id": 189, "width": 30, "left": 0 },
            { "id": 190, "width": 30, "left": 0 },
            { "id": 191, "width": 31, "left": 0 },
            { "id": 192, "width": 33, "left": 0 },
            { "id": 193, "width": 36, "left": 0 },
            { "id": 194, "width": 37, "left": 0 },
            { "id": 195, "width": 37, "left": 0 },
            { "id": 196, "width": 42, "left": 0 },
            { "id": 197, "width": 42, "left": 0 }
          ]
        }
      ]
    },
    {
      "page": 10,
      "rows": [
        {
          "id": 18,
          "top": 21,
          "height": 216,
          "blocks": [
            { "id": 198, "width": 60, "left": 37 },
            { "id": 199, "width": 40, "left": 0 },
            { "id": 200, "width": 40, "left": 0 },
            { "id": 201, "width": 43, "left": 0 },
            { "id": 202, "width": 42, "left": 0 },
            { "id": 203, "width": 43, "left": 0 },
            { "id": 204, "width": 42, "left": 0 },
            { "id": 205, "width": 42, "left": 0 },
            { "id": 206, "width": 41, "left": 0 },
            { "id": 207, "width": 42, "left": 0 }
          ]
        },
        {
          "id": 19,
          "top": 258,
          "height": 220,
          "blocks": [
            { "id": 208, "width": 61, "left": 34 },
            { "id": 209, "width": 41, "left": 0 },
            { "id": 210, "width": 42, "left": 0 },
            { "id": 211, "width": 42, "left": 0 },
            { "id": 212, "width": 42, "left": 0 },
            { "id": 213, "width": 42, "left": 0 },
            { "id": 214, "width": 42, "left": 0 },
            { "id": 215, "width": 41, "left": 0 },
            { "id": 216, "width": 41, "left": 0 },
            { "id": 217, "width": 42, "left": 0 }
          ]
        }
      ]
    },
    {
      "page": 11,
      "rows": [
        {
          "id": 20,
          "top": 27,
          "height": 217,
          "blocks": [
            { "id": 218, "width": 61, "left": 40 },
            { "id": 219, "width": 43, "left": 0 },
            { "id": 220, "width": 42, "left": 0 },
            { "id": 221, "width": 41, "left": 0 },
            { "id": 222, "width": 41, "left": 0 },
            { "id": 223, "width": 40, "left": 0 },
            { "id": 224, "width": 41, "left": 0 },
            { "id": 225, "width": 41, "left": 0 },
            { "id": 226, "width": 37, "left": 0 },
            { "id": 227, "width": 41, "left": 0 }
          ]
        },
        {
          "id": 21,
          "top": 261,
          "height": 207,
          "blocks": [
            { "id": 228, "width": 59, "left": 38 },
            { "id": 229, "width": 38, "left": 0 },
            { "id": 230, "width": 38, "left": 0 },
            { "id": 231, "width": 38, "left": 0 },
            { "id": 232, "width": 37, "left": 0 },
            { "id": 233, "width": 36, "left": 0 },
            { "id": 234, "width": 37, "left": 0 },
            { "id": 235, "width": 34, "left": 0 },
            { "id": 236, "width": 33, "left": 0 },
            { "id": 237, "width": 36, "left": 0 },
            { "id": 238, "width": 41, "left": 0 }
          ]
        }
      ]
    },
    {
      "page": 12,
      "rows": [
        {
          "id": 22,
          "top": 26,
          "height": 222,
          "blocks": [
            { "id": 239, "width": 58, "left": 38 },
            { "id": 240, "width": 41, "left": 0 },
            { "id": 241, "width": 41, "left": 0 },
            { "id": 242, "width": 46, "left": 0 },
            { "id": 243, "width": 29, "left": 0 },
            { "id": 244, "width": 25, "left": 0 },
            { "id": 245, "width": 26, "left": 0 },
            { "id": 246, "width": 38, "left": 0 },
            { "id": 247, "width": 43, "left": 0 },
            { "id": 248, "width": 43, "left": 0 },
            { "id": 249, "width": 44, "left": 0 }
          ]
        },
        {
          "id": 23,
          "top": 262,
          "height": 215,
          "blocks": [
            { "id": 250, "width": 73, "left": 34 },
            { "id": 251, "width": 51, "left": 0 },
            { "id": 252, "width": 52, "left": 0 },
            { "id": 253, "width": 54, "left": 0 },
            { "id": 254, "width": 52, "left": 0 },
            { "id": 255, "width": 51, "left": 0 },
            { "id": 256, "width": 50, "left": 0 },
            { "id": 257, "width": 53, "left": 0 }
          ]
        }
      ]
    },
    {
      "page": 13,
      "rows": [
        {
          "id": 24,
          "top": 20,
          "height": 217,
          "blocks": [
            { "id": 258, "width": 64, "left": 40 },
            { "id": 259, "width": 48, "left": 0 },
            { "id": 260, "width": 46, "left": 0 },
            { "id": 261, "width": 48, "left": 0 },
            { "id": 262, "width": 49, "left": 0 },
            { "id": 263, "width": 23, "left": 0 },
            { "id": 264, "width": 24, "left": 0 },
            { "id": 265, "width": 22, "left": 0 },
            { "id": 266, "width": 36, "left": 0 },
            { "id": 267, "width": 22, "left": 0 },
            { "id": 268, "width": 23, "left": 0 },
            { "id": 269, "width": 23, "left": 0 }
          ]
        },
        {
          "id": 25,
          "top": 254,
          "height": 216,
          "blocks": [
            { "id": 270, "width": 56, "left": 38 },
            { "id": 271, "width": 25, "left": 0 },
            { "id": 272, "width": 39, "left": 0 },
            { "id": 273, "width": 24, "left": 0 },
            { "id": 274, "width": 42, "left": 0 },
            { "id": 275, "width": 45, "left": 0 },
            { "id": 276, "width": 44, "left": 0 },
            { "id": 277, "width": 45, "left": 0 },
            { "id": 278, "width": 39, "left": 0 },
            { "id": 279, "width": 34, "left": 0 },
            { "id": 280, "width": 38, "left": 0 }
          ]
        }
      ]
    },
    {
      "page": 14,
      "rows": [
        {
          "id": 26,
          "top": 17,
          "height": 216,
          "blocks": [
            { "id": 281, "width": 61, "left": 37 },
            { "id": 282, "width": 16, "left": 0 },
            { "id": 283, "width": 15, "left": 0 },
            { "id": 284, "width": 28, "left": 0 },
            { "id": 285, "width": 29, "left": 0 },
            { "id": 286, "width": 29, "left": 0 },
            { "id": 287, "width": 29, "left": 0 },
            { "id": 288, "width": 30, "left": 0 },
            { "id": 289, "width": 37, "left": 0 },
            { "id": 290, "width": 42, "left": 0 },
            { "id": 291, "width": 38, "left": 0 },
            { "id": 292, "width": 42, "left": 0 },
            { "id": 293, "width": 39, "left": 0 }
          ]
        },
        {
          "id": 27,
          "top": 247,
          "height": 226,
          "blocks": [
            { "id": 294, "width": 61, "left": 31 },
            { "id": 295, "width": 41, "left": 0 },
            { "id": 296, "width": 43, "left": 0 },
            { "id": 297, "width": 40, "left": 0 },
            { "id": 298, "width": 39, "left": 0 },
            { "id": 299, "width": 38, "left": 0 },
            { "id": 300, "width": 42, "left": 0 },
            { "id": 301, "width": 44, "left": 0 },
            { "id": 302, "width": 44, "left": 0 },
            { "id": 303, "width": 45, "left": 0 }
          ]
        }
      ]
    },
    {
      "page": 15,
      "rows": [
        {
          "id": 28,
          "top": 22,
          "height": 222,
          "blocks": [
            { "id": 304, "width": 62, "left": 41 },
            { "id": 305, "width": 41, "left": 0 },
            { "id": 306, "width": 42, "left": 0 },
            { "id": 307, "width": 42, "left": 0 },
            { "id": 308, "width": 43, "left": 0 },
            { "id": 309, "width": 43, "left": 0 },
            { "id": 310, "width": 41, "left": 0 },
            { "id": 311, "width": 41, "left": 0 },
            { "id": 312, "width": 39, "left": 0 },
            { "id": 313, "width": 35, "left": 0 }
          ]
        },
        {
          "id": 29,
          "top": 260,
          "height": 212,
          "blocks": [
            { "id": 314, "width": 54, "left": 36 },
            { "id": 315, "width": 35, "left": 0 },
            { "id": 316, "width": 30, "left": 0 },
            { "id": 317, "width": 46, "left": 0 },
            { "id": 318, "width": 35, "left": 0 },
            { "id": 319, "width": 34, "left": 0 },
            { "id": 320, "width": 30, "left": 0 },
            { "id": 321, "width": 49, "left": 0 },
            { "id": 322, "width": 37, "left": 0 },
            { "id": 323, "width": 37, "left": 0 },
            { "id": 324, "width": 40, "left": 0 }
          ]
        }
      ]
    },
    {
      "page": 16,
      "rows": [
        {
          "id": 30,
          "top": 23,
          "height": 224,
          "blocks": [
            { "id": 325, "width": 55, "left": 36 },
            { "id": 326, "width": 43, "left": 0 },
            { "id": 327, "width": 44, "left": 0 },
            { "id": 328, "width": 39, "left": 0 },
            { "id": 329, "width": 28, "left": 0 },
            { "id": 330, "width": 30, "left": 0 },
            { "id": 331, "width": 29, "left": 0 },
            { "id": 332, "width": 25, "left": 0 },
            { "id": 333, "width": 29, "left": 0 },
            { "id": 334, "width": 30, "left": 0 },
            { "id": 335, "width": 28, "left": 0 },
            { "id": 336, "width": 25, "left": 0 },
            { "id": 337, "width": 31, "left": 0 }
          ]
        },
        {
          "id": 31,
          "top": 262,
          "height": 215,
          "blocks": [
            { "id": 338, "width": 48, "left": 33 },
            { "id": 339, "width": 33, "left": 0 },
            { "id": 340, "width": 26, "left": 0 },
            { "id": 341, "width": 33, "left": 0 },
            { "id": 342, "width": 33, "left": 0 },
            { "id": 343, "width": 33, "left": 0 },
            { "id": 344, "width": 35, "left": 0 },
            { "id": 345, "width": 35, "left": 0 },
            { "id": 346, "width": 32, "left": 0 },
            { "id": 347, "width": 32, "left": 0 },
            { "id": 348, "width": 31, "left": 0 },
            { "id": 349, "width": 32, "left": 0 },
            { "id": 350, "width": 33, "left": 0 }
          ]
        }
      ]
    },
    {
      "page": 17,
      "rows": [
        {
          "id": 32,
          "top": 17,
          "height": 209,
          "blocks": [
            { "id": 351, "width": 47, "left": 40 },
            { "id": 352, "width": 30, "left": 0 },
            { "id": 353, "width": 30, "left": 0 },
            { "id": 354, "width": 30, "left": 0 },
            { "id": 355, "width": 29, "left": 0 },
            { "id": 356, "width": 29, "left": 0 },
            { "id": 357, "width": 30, "left": 0 },
            { "id": 358, "width": 29, "left": 0 },
            { "id": 359, "width": 30, "left": 0 },
            { "id": 360, "width": 29, "left": 0 },
            { "id": 361, "width": 30, "left": 0 },
            { "id": 362, "width": 42, "left": 0 },
            { "id": 363, "width": 44, "left": 0 }
          ]
        },
        {
          "id": 33,
          "top": 249,
          "height": 226,
          "blocks": [
            { "id": 364, "width": 61, "left": 37 },
            { "id": 365, "width": 43, "left": 0 },
            { "id": 366, "width": 37, "left": 0 },
            { "id": 367, "width": 36, "left": 0 },
            { "id": 368, "width": 36, "left": 0 },
            { "id": 369, "width": 36, "left": 0 },
            { "id": 370, "width": 49, "left": 0 },
            { "id": 371, "width": 48, "left": 0 },
            { "id": 372, "width": 38, "left": 0 },
            { "id": 373, "width": 46, "left": 0 }
          ]
        }
      ]
    },
    {
      "page": 18,
      "rows": [
        {
          "id": 34,
          "top": 22,
          "height": 211,
          "blocks": [
            { "id": 374, "width": 54, "left": 37 },
            { "id": 375, "width": 25, "left": 0 },
            { "id": 376, "width": 31, "left": 0 },
            { "id": 377, "width": 29, "left": 0 },
            { "id": 378, "width": 30, "left": 0 },
            { "id": 379, "width": 33, "left": 0 },
            { "id": 380, "width": 36, "left": 0 },
            { "id": 381, "width": 44, "left": 0 },
            { "id": 382, "width": 28, "left": 0 },
            { "id": 383, "width": 30, "left": 0 },
            { "id": 384, "width": 30, "left": 0 },
            { "id": 385, "width": 31, "left": 0 },
            { "id": 386, "width": 35, "left": 0 }
          ]
        },
        {
          "id": 35,
          "top": 253,
          "height": 222,
          "blocks": [
            { "id": 387, "width": 50, "left": 31 },
            { "id": 388, "width": 31, "left": 0 },
            { "id": 389, "width": 32, "left": 0 },
            { "id": 390, "width": 49, "left": 0 },
            { "id": 391, "width": 47, "left": 0 },
            { "id": 392, "width": 47, "left": 0 },
            { "id": 393, "width": 47, "left": 0 },
            { "id": 394, "width": 43, "left": 0 },
            { "id": 395, "width": 44, "left": 0 },
            { "id": 396, "width": 48, "left": 0 }
          ]
        }
      ]
    },
    {
      "page": 19,
      "rows": [
        {
          "id": 36,
          "top": 22,
          "height": 227,
          "blocks": [
            { "id": 397, "width": 59, "left": 41 },
            { "id": 398, "width": 39, "left": 0 },
            { "id": 399, "width": 40, "left": 0 },
            { "id": 400, "width": 38, "left": 0 },
            { "id": 401, "width": 41, "left": 0 },
            { "id": 402, "width": 42, "left": 0 },
            { "id": 403, "width": 43, "left": 0 },
            { "id": 404, "width": 42, "left": 0 },
            { "id": 405, "width": 42, "left": 0 },
            { "id": 406, "width": 43, "left": 0 }
          ]
        },
        {
          "id": 37,
          "top": 264,
          "height": 209,
          "blocks": [
            { "id": 407, "width": 61, "left": 35 },
            { "id": 408, "width": 42, "left": 0 },
            { "id": 409, "width": 40, "left": 0 },
            { "id": 410, "width": 40, "left": 0 },
            { "id": 411, "width": 40, "left": 0 },
            { "id": 412, "width": 41, "left": 0 },
            { "id": 413, "width": 39, "left": 0 },
            { "id": 414, "width": 31, "left": 0 },
            { "id": 415, "width": 31, "left": 0 },
            { "id": 416, "width": 30, "left": 0 },
            { "id": 417, "width": 35, "left": 0 }
          ]
        }
      ]
    },
    {
      "page": 20,
      "rows": [
        {
          "id": 38,
          "top": 28,
          "height": 212,
          "blocks": [
            { "id": 418, "width": 51, "left": 37 },
            { "id": 419, "width": 32, "left": 0 },
            { "id": 420, "width": 29, "left": 0 },
            { "id": 421, "width": 34, "left": 0 },
            { "id": 422, "width": 30, "left": 0 },
            { "id": 423, "width": 33, "left": 0 },
            { "id": 424, "width": 37, "left": 0 },
            { "id": 425, "width": 35, "left": 0 },
            { "id": 426, "width": 36, "left": 0 },
            { "id": 427, "width": 34, "left": 0 },
            { "id": 428, "width": 44, "left": 0 },
            { "id": 429, "width": 41, "left": 0 }
          ]
        },
        {
          "id": 39,
          "top": 263,
          "height": 218,
          "blocks": [
            { "id": 430, "width": 57, "left": 31 },
            { "id": 431, "width": 40, "left": 0 },
            { "id": 432, "width": 37, "left": 0 },
            { "id": 433, "width": 39, "left": 0 },
            { "id": 434, "width": 37, "left": 0 },
            { "id": 435, "width": 39, "left": 0 },
            { "id": 436, "width": 37, "left": 0 },
            { "id": 437, "width": 37, "left": 0 },
            { "id": 438, "width": 40, "left": 0 },
            { "id": 439, "width": 37, "left": 0 },
            { "id": 440, "width": 38, "left": 0 }
          ]
        }
      ]
    },
    {
      "page": 21,
      "rows": [
        {
          "id": 40,
          "top": 25,
          "height": 216,
          "blocks": [
            { "id": 441, "width": 57, "left": 40 },
            { "id": 442, "width": 36, "left": 0 },
            { "id": 443, "width": 39, "left": 0 },
            { "id": 444, "width": 37, "left": 0 },
            { "id": 445, "width": 38, "left": 0 },
            { "id": 446, "width": 36, "left": 0 },
            { "id": 447, "width": 39, "left": 0 },
            { "id": 448, "width": 38, "left": 0 },
            { "id": 449, "width": 37, "left": 0 },
            { "id": 450, "width": 35, "left": 0 },
            { "id": 451, "width": 36, "left": 0 }
          ]
        },
        {
          "id": 41,
          "top": 266,
          "height": 213,
          "blocks": [
            { "id": 452, "width": 56, "left": 36 },
            { "id": 453, "width": 38, "left": 0 },
            { "id": 454, "width": 37, "left": 0 },
            { "id": 455, "width": 37, "left": 0 },
            { "id": 456, "width": 37, "left": 0 },
            { "id": 457, "width": 37, "left": 0 },
            { "id": 458, "width": 37, "left": 0 },
            { "id": 459, "width": 37, "left": 0 },
            { "id": 460, "width": 36, "left": 0 },
            { "id": 461, "width": 37, "left": 0 },
            { "id": 462, "width": 39, "left": 0 }
          ]
        }
      ]
    },
    {
      "page": 22,
      "rows": [
        {
          "id": 42,
          "top": 22,
          "height": 212,
          "blocks": [
            { "id": 463, "width": 58, "left": 40 },
            { "id": 464, "width": 39, "left": 0 },
            { "id": 465, "width": 38, "left": 0 },
            { "id": 466, "width": 39, "left": 0 },
            { "id": 467, "width": 39, "left": 0 },
            { "id": 468, "width": 35, "left": 0 },
            { "id": 469, "width": 36, "left": 0 },
            { "id": 470, "width": 37, "left": 0 },
            { "id": 471, "width": 35, "left": 0 },
            { "id": 472, "width": 35, "left": 0 },
            { "id": 473, "width": 42, "left": 0 }
          ]
        },
        {
          "id": 43,
          "top": 254,
          "height": 219,
          "blocks": [
            { "id": 474, "width": 54, "left": 35 },
            { "id": 475, "width": 35, "left": 0 },
            { "id": 476, "width": 36, "left": 0 },
            { "id": 477, "width": 36, "left": 0 },
            { "id": 478, "width": 36, "left": 0 },
            { "id": 479, "width": 40, "left": 0 },
            { "id": 480, "width": 40, "left": 0 },
            { "id": 481, "width": 40, "left": 0 },
            { "id": 482, "width": 40, "left": 0 },
            { "id": 483, "width": 40, "left": 0 },
            { "id": 484, "width": 39, "left": 0 }
          ]
        }
      ]
    },
    {
      "page": 23,
      "rows": [
        {
          "id": 44,
          "top": 18,
          "height": 217,
          "blocks": [
            { "id": 485, "width": 56, "left": 40 },
            { "id": 486, "width": 37, "left": 0 },
            { "id": 487, "width": 36, "left": 0 },
            { "id": 488, "width": 37, "left": 0 },
            { "id": 489, "width": 36, "left": 0 },
            { "id": 490, "width": 37, "left": 0 },
            { "id": 491, "width": 36, "left": 0 },
            { "id": 492, "width": 27, "left": 0 },
            { "id": 493, "width": 32, "left": 0 },
            { "id": 494, "width": 31, "left": 0 },
            { "id": 495, "width": 31, "left": 0 },
            { "id": 496, "width": 33, "left": 0 }
          ]
        },
        {
          "id": 45,
          "top": 258,
          "height": 217,
          "blocks": [
            { "id": 497, "width": 49, "left": 36 },
            { "id": 498, "width": 33, "left": 0 },
            { "id": 499, "width": 33, "left": 0 },
            { "id": 500, "width": 32, "left": 0 },
            { "id": 501, "width": 28, "left": 0 },
            { "id": 502, "width": 22, "left": 0 },
            { "id": 503, "width": 28, "left": 0 },
            { "id": 504, "width": 23, "left": 0 },
            { "id": 505, "width": 29, "left": 0 },
            { "id": 506, "width": 20, "left": 0 },
            { "id": 507, "width": 19, "left": 0 },
            { "id": 508, "width": 19, "left": 0 },
            { "id": 509, "width": 26, "left": 0 },
            { "id": 510, "width": 19, "left": 0 },
            { "id": 511, "width": 21, "left": 0 },
            { "id": 512, "width": 26, "left": 0 }
          ]
        }
      ]
    },
    {
      "page": 24,
      "rows": [
        {
          "id": 46,
          "top": 29,
          "height": 204,
          "blocks": [
            { "id": 1001, "width": 111, "left": 102 },
            { "id": 1002, "width": 84, "left": 0 },
            { "id": 1003, "width": 92, "left": 0 },
            { "id": 1004, "width": 80, "left": 0 }
          ]
        },
        {
          "id": 47,
          "top": 249,
          "height": 219,
          "blocks": [
            { "id": 1005, "width": 95, "left": 38 },
            { "id": 1006, "width": 95, "left": 0 },
            { "id": 1007, "width": 121, "left": 0 },
            { "id": 1008, "width": 119, "left": 0 }
          ]
        }
      ]
    },
    {
      "page": 25,
      "rows": [
        {
          "id": 48,
          "top": 24,
          "height": 214,
          "blocks": [
            { "id": 1009, "width": 179, "left": 42 },
            { "id": 1010, "width": 153, "left": 0 },
            { "id": 1011, "width": 93, "left": 0 }
          ]
        },
        {
          "id": 49,
          "top": 254,
          "height": 215,
          "blocks": [
            { "id": 1012, "width": 122, "left": 38 },
            { "id": 1013, "width": 65, "left": 0 },
            { "id": 1014, "width": 84, "left": 0 },
            { "id": 1015, "width": 65, "left": 0 },
            { "id": 1016, "width": 91, "left": 0 }
          ]
        }
      ]
    },
    {
      "page": 26,
      "rows": [
        {
          "id": 50,
          "top": 26,
          "height": 218,
          "blocks": [
            { "id": 1017, "width": 100, "left": 39 },
            { "id": 1018, "width": 65, "left": 0 },
            { "id": 1019, "width": 79, "left": 0 },
            { "id": 1020, "width": 61, "left": 0 },
            { "id": 1021, "width": 123, "left": 0 }
          ]
        },
        {
          "id": 51,
          "top": 259,
          "height": 211,
          "blocks": [
            { "id": 1022, "width": 153, "left": 37 },
            { "id": 1023, "width": 139, "left": 0 },
            { "id": 1024, "width": 138, "left": 0 }
          ]
        }
      ]
    },
    {
      "page": 27,
      "rows": [
        {
          "id": 52,
          "top": 25,
          "height": 212,
          "blocks": [
            { "id": 1025, "width": 157, "left": 42 },
            { "id": 1026, "width": 144, "left": 0 },
            { "id": 1027, "width": 123, "left": 0 }
          ]
        },
        {
          "id": 53,
          "top": 258,
          "height": 215,
          "blocks": [
            { "id": 1028, "width": 143, "left": 40 },
            { "id": 1029, "width": 140, "left": 0 },
            { "id": 1030, "width": 143, "left": 0 }
          ]
        }
      ]
    },
    {
      "page": 28,
      "rows": [
        {
          "id": 54,
          "top": 21,
          "height": 218,
          "blocks": [
            { "id": 1031, "width": 155, "left": 38 },
            { "id": 1032, "width": 136, "left": 0 },
            { "id": 1033, "width": 140, "left": 0 }
          ]
        },
        {
          "id": 55,
          "top": 254,
          "height": 217,
          "blocks": [
            { "id": 1034, "width": 157, "left": 34 },
            { "id": 1035, "width": 137, "left": 0 },
            { "id": 1036, "width": 139, "left": 0 }
          ]
        }
      ]
    },
    {
      "page": 29,
      "rows": [
        {
          "id": 56,
          "top": 29,
          "height": 211,
          "blocks": [
            { "id": 1037, "width": 165, "left": 42 },
            { "id": 1038, "width": 84, "left": 0 },
            { "id": 1039, "width": 94, "left": 0 },
            { "id": 1040, "width": 82, "left": 0 }
          ]
        },
        {
          "id": 57,
          "top": 261,
          "height": 213,
          "blocks": [
            { "id": 1041, "width": 144, "left": 38 },
            { "id": 1042, "width": 115, "left": 0 },
            { "id": 1043, "width": 96, "left": 0 },
            { "id": 1044, "width": 72, "left": 0 }
          ]
        }
      ]
    },
    {
      "page": 30,
      "rows": [
        {
          "id": 58,
          "top": 26,
          "height": 218,
          "blocks": [
            { "id": 1045, "width": 106, "left": 38 },
            { "id": 1046, "width": 73, "left": 0 },
            { "id": 1047, "width": 74, "left": 0 },
            { "id": 1048, "width": 73, "left": 0 },
            { "id": 1049, "width": 104, "left": 0 }
          ]
        },
        {
          "id": 59,
          "top": 266,
          "height": 211,
          "blocks": [
            { "id": 1050, "width": 159, "left": 37 },
            { "id": 1051, "width": 136, "left": 0 },
            { "id": 1052, "width": 134, "left": 0 }
          ]
        }
      ]
    },
    {
      "page": 31,
      "rows": [
        {
          "id": 60,
          "top": 20,
          "height": 214,
          "blocks": [
            { "id": 1053, "width": 159, "left": 41 },
            { "id": 1054, "width": 131, "left": 0 },
            { "id": 1055, "width": 134, "left": 0 }
          ]
        },
        {
          "id": 61,
          "top": 252,
          "height": 218,
          "blocks": [
            { "id": 1056, "width": 150, "left": 40 },
            { "id": 1057, "width": 132, "left": 0 },
            { "id": 1058, "width": 144, "left": 0 }
          ]
        }
      ]
    },
    {
      "page": 32,
      "rows": [
        {
          "id": 62,
          "top": 25,
          "height": 205,
          "blocks": [
            { "id": 1059, "width": 157, "left": 40 },
            { "id": 1060, "width": 141, "left": 0 },
            { "id": 1061, "width": 131, "left": 0 }
          ]
        },
        {
          "id": 63,
          "top": 253,
          "height": 218,
          "blocks": [
            { "id": 1062, "width": 112, "left": 36 },
            { "id": 1063, "width": 88, "left": 0 },
            { "id": 1064, "width": 123, "left": 0 },
            { "id": 1065, "width": 108, "left": 0 }
          ]
        }
      ]
    },
    {
      "page": 33,
      "rows": [
        {
          "id": 64,
          "top": 25,
          "height": 223,
          "blocks": [
            { "id": 1066, "width": 112, "left": 40 },
            { "id": 1067, "width": 89, "left": 0 },
            { "id": 1068, "width": 108, "left": 0 },
            { "id": 1069, "width": 119, "left": 0 }
          ]
        },
        {
          "id": 65,
          "top": 263,
          "height": 209,
          "blocks": [
            { "id": 1070, "width": 152, "left": 37 },
            { "id": 1071, "width": 138, "left": 0 },
            { "id": 1072, "width": 139, "left": 0 }
          ]
        }
      ]
    },
    {
      "page": 34,
      "rows": [
        {
          "id": 66,
          "top": 19,
          "height": 213,
          "blocks": [
            { "id": 1073, "width": 103, "left": 37 },
            { "id": 1074, "width": 95, "left": 0 },
            { "id": 1075, "width": 127, "left": 0 },
            { "id": 1076, "width": 109, "left": 0 }
          ]
        },
        {
          "id": 67,
          "top": 248,
          "height": 226,
          "blocks": [
            { "id": 1077, "width": 85, "left": 35 },
            { "id": 1078, "width": 86, "left": 0 },
            { "id": 1079, "width": 101, "left": 0 },
            { "id": 1080, "width": 80, "left": 0 },
            { "id": 1081, "width": 82, "left": 0 }
          ]
        }
      ]
    },
    {
      "page": 35,
      "rows": [
        {
          "id": 68,
          "top": 21,
          "height": 214,
          "blocks": [
            { "id": 1082, "width": 135, "left": 40 },
            { "id": 1083, "width": 100, "left": 0 },
            { "id": 1084, "width": 99, "left": 0 },
            { "id": 1085, "width": 94, "left": 0 }
          ]
        },
        {
          "id": 69,
          "top": 254,
          "height": 219,
          "blocks": [
            { "id": 1086, "width": 159, "left": 36 },
            { "id": 1087, "width": 136, "left": 0 },
            { "id": 1088, "width": 135, "left": 0 }
          ]
        }
      ]
    },
    {
      "page": 36,
      "rows": [
        {
          "id": 70,
          "top": 24,
          "height": 213,
          "blocks": [
            { "id": 1089, "width": 156, "left": 38 },
            { "id": 1090, "width": 134, "left": 0 },
            { "id": 1091, "width": 142, "left": 0 }
          ]
        },
        {
          "id": 71,
          "top": 260,
          "height": 218,
          "blocks": [
            { "id": 1092, "width": 157, "left": 36 },
            { "id": 1093, "width": 143, "left": 0 },
            { "id": 1094, "width": 134, "left": 0 }
          ]
        }
      ]
    },
    {
      "page": 37,
      "rows": [
        {
          "id": 72,
          "top": 23,
          "height": 220,
          "blocks": [
            { "id": 1095, "width": 98, "left": 40 },
            { "id": 1096, "width": 94, "left": 0 },
            { "id": 1097, "width": 113, "left": 0 },
            { "id": 1098, "width": 122, "left": 0 }
          ]
        },
        {
          "id": 73,
          "top": 262,
          "height": 211,
          "blocks": [
            { "id": 1099, "width": 158, "left": 38 },
            { "id": 1100, "width": 129, "left": 0 },
            { "id": 1101, "width": 142, "left": 0 }
          ]
        }
      ]
    },
    {
      "page": 38,
      "rows": [
        {
          "id": 74,
          "top": 28,
          "height": 219,
          "blocks": [
            { "id": 1102, "width": 158, "left": 37 },
            { "id": 1103, "width": 135, "left": 0 },
            { "id": 1104, "width": 138, "left": 0 }
          ]
        },
        {
          "id": 75,
          "top": 264,
          "height": 208,
          "blocks": [
            { "id": 1105, "width": 157, "left": 35 },
            { "id": 1106, "width": 136, "left": 0 },
            { "id": 1107, "width": 138, "left": 0 }
          ]
        }
      ]
    },
    {
      "page": 39,
      "rows": [
        {
          "id": 76,
          "top": 23,
          "height": 217,
          "blocks": [
            { "id": 1108, "width": 153, "left": 39 },
            { "id": 1109, "width": 124, "left": 0 },
            { "id": 1110, "width": 72, "left": 0 },
            { "id": 1111, "width": 78, "left": 0 }
          ]
        },
        {
          "id": 77,
          "top": 259,
          "height": 208,
          "blocks": [
            { "id": 1112, "width": 93, "left": 38 },
            { "id": 1113, "width": 124, "left": 0 },
            { "id": 1114, "width": 116, "left": 0 },
            { "id": 1115, "width": 95, "left": 0 }
          ]
        }
      ]
    },
    {
      "page": 40,
      "rows": [
        {
          "id": 78,
          "top": 25,
          "height": 217,
          "blocks": [
            { "id": 1116, "width": 105, "left": 38 },
            { "id": 1117, "width": 88, "left": 0 },
            { "id": 1118, "width": 81, "left": 0 },
            { "id": 1119, "width": 80, "left": 0 },
            { "id": 1120, "width": 79, "left": 0 }
          ]
        },
        {
          "id": 79,
          "top": 261,
          "height": 216,
          "blocks": [
            { "id": 1121, "width": 151, "left": 35 },
            { "id": 1122, "width": 141, "left": 0 },
            { "id": 1123, "width": 141, "left": 0 }
          ]
        }
      ]
    },
    {
      "page": 41,
      "rows": [
        {
          "id": 80,
          "top": 22,
          "height": 217,
          "blocks": [
            { "id": 1124, "width": 148, "left": 40 },
            { "id": 1125, "width": 134, "left": 0 },
            { "id": 1126, "width": 144, "left": 0 }
          ]
        },
        {
          "id": 81,
          "top": 257,
          "height": 214,
          "blocks": [
            { "id": 1127, "width": 171, "left": 38 },
            { "id": 1128, "width": 160, "left": 0 },
            { "id": 1129, "width": 96, "left": 0 }
          ]
        }
      ]
    },
    {
      "page": 42,
      "rows": [
        {
          "id": 82,
          "top": 22,
          "height": 202,
          "blocks": [
            { "id": 1130, "width": 108, "left": 39 },
            { "id": 1131, "width": 78, "left": 0 },
            { "id": 1132, "width": 84, "left": 0 },
            { "id": 1133, "width": 69, "left": 0 },
            { "id": 1134, "width": 93, "left": 0 }
          ]
        },
        {
          "id": 83,
          "top": 244,
          "height": 227,
          "blocks": [
            { "id": 1135, "width": 112, "left": 35 },
            { "id": 1136, "width": 95, "left": 0 },
            { "id": 1137, "width": 84, "left": 0 },
            { "id": 1138, "width": 77, "left": 0 },
            { "id": 1139, "width": 65, "left": 0 }
          ]
        }
      ]
    },
    {
      "page": 43,
      "rows": [
        {
          "id": 84,
          "top": 40,
          "height": 211,
          "blocks": [
            { "id": 2000, "width": 17, "left": 129 },
            { "id": 2001, "width": 22, "left": 0 },
            { "id": 2002, "width": 22, "left": 0 },
            { "id": 2003, "width": 22, "left": 0 },
            { "id": 2004, "width": 22, "left": 0 },
            { "id": 2005, "width": 25, "left": 0 },
            { "id": 2006, "width": 24, "left": 0 },
            { "id": 2007, "width": 25, "left": 0 },
            { "id": 2008, "width": 22, "left": 0 },
            { "id": 2009, "width": 23, "left": 0 },
            { "id": 2010, "width": 26, "left": 0 },
            { "id": 2011, "width": 32, "left": 0 },
            { "id": 2012, "width": 22, "left": 0 },
            { "id": 2013, "width": 32, "left": 0 }
          ]
        },
        {
          "id": 85,
          "top": 269,
          "height": 205,
          "blocks": [
            { "id": 2014, "width": 50, "left": 36 },
            { "id": 2015, "width": 36, "left": 0 },
            { "id": 2016, "width": 25, "left": 0 },
            { "id": 2017, "width": 27, "left": 0 },
            { "id": 2018, "width": 24, "left": 0 },
            { "id": 2019, "width": 24, "left": 0 },
            { "id": 2020, "width": 25, "left": 0 },
            { "id": 2021, "width": 27, "left": 0 },
            { "id": 2022, "width": 27, "left": 0 },
            { "id": 2023, "width": 27, "left": 0 },
            { "id": 2024, "width": 25, "left": 0 },
            { "id": 2025, "width": 25, "left": 0 },
            { "id": 2026, "width": 27, "left": 0 },
            { "id": 2027, "width": 36, "left": 0 },
            { "id": 2028, "width": 25, "left": 0 }
          ]
        }
      ]
    },
    {
      "page": 44,
      "rows": [
        {
          "id": 86,
          "top": 23,
          "height": 209,
          "blocks": [
            { "id": 2029, "width": 53, "left": 38 },
            { "id": 2030, "width": 35, "left": 0 },
            { "id": 2031, "width": 38, "left": 0 },
            { "id": 2032, "width": 28, "left": 0 },
            { "id": 2033, "width": 28, "left": 0 },
            { "id": 2034, "width": 29, "left": 0 },
            { "id": 2035, "width": 28, "left": 0 },
            { "id": 2036, "width": 28, "left": 0 },
            { "id": 2037, "width": 26, "left": 0 },
            { "id": 2038, "width": 28, "left": 0 },
            { "id": 2039, "width": 28, "left": 0 },
            { "id": 2040, "width": 28, "left": 0 },
            { "id": 2041, "width": 26, "left": 0 },
            { "id": 2042, "width": 27, "left": 0 }
          ]
        },
        {
          "id": 87,
          "top": 248,
          "height": 228,
          "blocks": [
            { "id": 2043, "width": 55, "left": 35 },
            { "id": 2044, "width": 28, "left": 0 },
            { "id": 2045, "width": 26, "left": 0 },
            { "id": 2046, "width": 27, "left": 0 },
            { "id": 2047, "width": 29, "left": 0 },
            { "id": 2048, "width": 26, "left": 0 },
            { "id": 2049, "width": 27, "left": 0 },
            { "id": 2050, "width": 27, "left": 0 },
            { "id": 2051, "width": 26, "left": 0 },
            { "id": 2052, "width": 26, "left": 0 },
            { "id": 2053, "width": 26, "left": 0 },
            { "id": 2054, "width": 28, "left": 0 },
            { "id": 2055, "width": 27, "left": 0 },
            { "id": 2056, "width": 27, "left": 0 },
            { "id": 2057, "width": 27, "left": 0 }
          ]
        }
      ]
    },
    {
      "page": 45,
      "rows": [
        {
          "id": 88,
          "top": 23,
          "height": 221,
          "blocks": [
            { "id": 2058, "width": 45, "left": 40 },
            { "id": 2059, "width": 18, "left": 0 },
            { "id": 2060, "width": 28, "left": 0 },
            { "id": 2061, "width": 29, "left": 0 },
            { "id": 2062, "width": 23, "left": 0 },
            { "id": 2063, "width": 18, "left": 0 },
            { "id": 2064, "width": 18, "left": 0 },
            { "id": 2065, "width": 17, "left": 0 },
            { "id": 2066, "width": 18, "left": 0 },
            { "id": 2067, "width": 26, "left": 0 },
            { "id": 2068, "width": 29, "left": 0 },
            { "id": 2069, "width": 31, "left": 0 },
            { "id": 2070, "width": 23, "left": 0 },
            { "id": 2071, "width": 18, "left": 0 },
            { "id": 2072, "width": 18, "left": 0 },
            { "id": 2073, "width": 18, "left": 0 },
            { "id": 2074, "width": 17, "left": 0 },
            { "id": 2075, "width": 34, "left": 0 }
          ]
        },
        {
          "id": 89,
          "top": 262,
          "height": 210,
          "blocks": [
            { "id": 2076, "width": 53, "left": 37 },
            { "id": 2077, "width": 32, "left": 0 },
            { "id": 2078, "width": 27, "left": 0 },
            { "id": 2079, "width": 34, "left": 0 },
            { "id": 2080, "width": 32, "left": 0 },
            { "id": 2081, "width": 32, "left": 0 },
            { "id": 2082, "width": 28, "left": 0 },
            { "id": 2083, "width": 28, "left": 0 },
            { "id": 2084, "width": 27, "left": 0 },
            { "id": 2085, "width": 27, "left": 0 },
            { "id": 2086, "width": 27, "left": 0 },
            { "id": 2087, "width": 27, "left": 0 },
            { "id": 2088, "width": 27, "left": 0 },
            { "id": 2089, "width": 28, "left": 0 }
          ]
        }
      ]
    },
    {
      "page": 46,
      "rows": [
        {
          "id": 90,
          "top": 19,
          "height": 212,
          "blocks": [
            { "id": 2090, "width": 46, "left": 39 },
            { "id": 2091, "width": 27, "left": 0 },
            { "id": 2092, "width": 26, "left": 0 },
            { "id": 2093, "width": 30, "left": 0 },
            { "id": 2094, "width": 27, "left": 0 },
            { "id": 2095, "width": 27, "left": 0 },
            { "id": 2096, "width": 26, "left": 0 },
            { "id": 2097, "width": 27, "left": 0 },
            { "id": 2098, "width": 27, "left": 0 },
            { "id": 2099, "width": 26, "left": 0 },
            { "id": 2100, "width": 27, "left": 0 },
            { "id": 2101, "width": 30, "left": 0 },
            { "id": 2102, "width": 27, "left": 0 },
            { "id": 2103, "width": 27, "left": 0 },
            { "id": 2104, "width": 29, "left": 0 }
          ]
        },
        {
          "id": 91,
          "top": 247,
          "height": 221,
          "blocks": [
            { "id": 2105, "width": 45, "left": 37 },
            { "id": 2106, "width": 25, "left": 0 },
            { "id": 2107, "width": 25, "left": 0 },
            { "id": 2108, "width": 26, "left": 0 },
            { "id": 2109, "width": 28, "left": 0 },
            { "id": 2110, "width": 26, "left": 0 },
            { "id": 2111, "width": 25, "left": 0 },
            { "id": 2112, "width": 25, "left": 0 },
            { "id": 2113, "width": 26, "left": 0 },
            { "id": 2114, "width": 24, "left": 0 },
            { "id": 2115, "width": 26, "left": 0 },
            { "id": 2116, "width": 25, "left": 0 },
            { "id": 2117, "width": 29, "left": 0 },
            { "id": 2118, "width": 25, "left": 0 },
            { "id": 2119, "width": 25, "left": 0 },
            { "id": 2120, "width": 26, "left": 0 }
          ]
        }
      ]
    },
    {
      "page": 47,
      "rows": [
        {
          "id": 92,
          "top": 20,
          "height": 219,
          "blocks": [
            { "id": 2121, "width": 45, "left": 40 },
            { "id": 2122, "width": 24, "left": 0 },
            { "id": 2123, "width": 25, "left": 0 },
            { "id": 2124, "width": 24, "left": 0 },
            { "id": 2125, "width": 32, "left": 0 },
            { "id": 2126, "width": 27, "left": 0 },
            { "id": 2127, "width": 25, "left": 0 },
            { "id": 2128, "width": 29, "left": 0 },
            { "id": 2129, "width": 24, "left": 0 },
            { "id": 2130, "width": 25, "left": 0 },
            { "id": 2131, "width": 35, "left": 0 },
            { "id": 2132, "width": 34, "left": 0 },
            { "id": 2133, "width": 24, "left": 0 },
            { "id": 2134, "width": 24, "left": 0 },
            { "id": 2135, "width": 29, "left": 0 }
          ]
        },
        {
          "id": 93,
          "top": 255,
          "height": 218,
          "blocks": [
            { "id": 2136, "width": 48, "left": 37 },
            { "id": 2137, "width": 25, "left": 0 },
            { "id": 2138, "width": 25, "left": 0 },
            { "id": 2139, "width": 24, "left": 0 },
            { "id": 2140, "width": 25, "left": 0 },
            { "id": 2141, "width": 26, "left": 0 },
            { "id": 2142, "width": 25, "left": 0 },
            { "id": 2143, "width": 27, "left": 0 },
            { "id": 2144, "width": 28, "left": 0 },
            { "id": 2145, "width": 25, "left": 0 },
            { "id": 2146, "width": 24, "left": 0 },
            { "id": 2147, "width": 25, "left": 0 },
            { "id": 2148, "width": 24, "left": 0 },
            { "id": 2149, "width": 26, "left": 0 },
            { "id": 2150, "width": 24, "left": 0 },
            { "id": 2151, "width": 26, "left": 0 }
          ]
        }
      ]
    },
    {
      "page": 48,
      "rows": [
        {
          "id": 94,
          "top": 21,
          "height": 223,
          "blocks": [
            { "id": 2152, "width": 43, "left": 37 },
            { "id": 2153, "width": 24, "left": 0 },
            { "id": 2154, "width": 24, "left": 0 },
            { "id": 2155, "width": 20, "left": 0 },
            { "id": 2156, "width": 24, "left": 0 },
            { "id": 2157, "width": 21, "left": 0 },
            { "id": 2158, "width": 24, "left": 0 },
            { "id": 2159, "width": 21, "left": 0 },
            { "id": 2160, "width": 23, "left": 0 },
            { "id": 2161, "width": 24, "left": 0 },
            { "id": 2162, "width": 25, "left": 0 },
            { "id": 2163, "width": 23, "left": 0 },
            { "id": 2164, "width": 26, "left": 0 },
            { "id": 2165, "width": 44, "left": 0 },
            { "id": 2166, "width": 25, "left": 0 },
            { "id": 2167, "width": 43, "left": 0 }
          ]
        },
        {
          "id": 95,
          "top": 264,
          "height": 213,
          "blocks": [
            { "id": 2168, "width": 52, "left": 35 },
            { "id": 2169, "width": 36, "left": 0 },
            { "id": 2170, "width": 27, "left": 0 },
            { "id": 2171, "width": 43, "left": 0 },
            { "id": 2172, "width": 33, "left": 0 },
            { "id": 2173, "width": 36, "left": 0 },
            { "id": 2174, "width": 27, "left": 0 },
            { "id": 2175, "width": 44, "left": 0 },
            { "id": 2176, "width": 32, "left": 0 },
            { "id": 2177, "width": 34, "left": 0 },
            { "id": 2178, "width": 27, "left": 0 },
            { "id": 2179, "width": 44, "left": 0 }
          ]
        }
      ]
    },
    {
      "page": 49,
      "rows": [
        {
          "id": 96,
          "top": 23,
          "height": 212,
          "blocks": [
            { "id": 2180, "width": 49, "left": 38 },
            { "id": 2181, "width": 35, "left": 0 },
            { "id": 2182, "width": 24, "left": 0 },
            { "id": 2183, "width": 40, "left": 0 },
            { "id": 2184, "width": 34, "left": 0 },
            { "id": 2185, "width": 35, "left": 0 },
            { "id": 2186, "width": 24, "left": 0 },
            { "id": 2187, "width": 39, "left": 0 },
            { "id": 2188, "width": 30, "left": 0 },
            { "id": 2189, "width": 39, "left": 0 },
            { "id": 2190, "width": 36, "left": 0 },
            { "id": 2191, "width": 43, "left": 0 }
          ]
        },
        {
          "id": 97,
          "top": 254,
          "height": 223,
          "blocks": [
            { "id": 2192, "width": 59, "left": 37 },
            { "id": 2193, "width": 41, "left": 0 },
            { "id": 2194, "width": 38, "left": 0 },
            { "id": 2195, "width": 35, "left": 0 },
            { "id": 2196, "width": 36, "left": 0 },
            { "id": 2197, "width": 38, "left": 0 },
            { "id": 2198, "width": 37, "left": 0 },
            { "id": 2199, "width": 34, "left": 0 },
            { "id": 2200, "width": 37, "left": 0 },
            { "id": 2201, "width": 37, "left": 0 },
            { "id": 2202, "width": 40, "left": 0 }
          ]
        }
      ]
    },
    {
      "page": 50,
      "rows": [
        {
          "id": 98,
          "top": 16,
          "height": 216,
          "blocks": [
            { "id": 2203, "width": 44, "left": 34 },
            { "id": 2204, "width": 23, "left": 0 },
            { "id": 2205, "width": 22, "left": 0 },
            { "id": 2206, "width": 24, "left": 0 },
            { "id": 2207, "width": 24, "left": 0 },
            { "id": 2208, "width": 25, "left": 0 },
            { "id": 2209, "width": 24, "left": 0 },
            { "id": 2210, "width": 27, "left": 0 },
            { "id": 2211, "width": 26, "left": 0 },
            { "id": 2212, "width": 27, "left": 0 },
            { "id": 2213, "width": 24, "left": 0 },
            { "id": 2214, "width": 24, "left": 0 },
            { "id": 2215, "width": 26, "left": 0 },
            { "id": 2216, "width": 33, "left": 0 },
            { "id": 2217, "width": 32, "left": 0 },
            { "id": 2218, "width": 32, "left": 0 }
          ]
        },
        {
          "id": 99,
          "top": 253,
          "height": 221,
          "blocks": [
            { "id": 2219, "width": 50, "left": 32 },
            { "id": 2220, "width": 28, "left": 0 },
            { "id": 2221, "width": 18, "left": 0 },
            { "id": 2222, "width": 27, "left": 0 },
            { "id": 2223, "width": 32, "left": 0 },
            { "id": 2224, "width": 27, "left": 0 },
            { "id": 2225, "width": 28, "left": 0 },
            { "id": 2226, "width": 31, "left": 0 },
            { "id": 2227, "width": 27, "left": 0 },
            { "id": 2228, "width": 29, "left": 0 },
            { "id": 2229, "width": 27, "left": 0 },
            { "id": 2230, "width": 27, "left": 0 },
            { "id": 2231, "width": 29, "left": 0 },
            { "id": 2232, "width": 27, "left": 0 },
            { "id": 2233, "width": 30, "left": 0 }
          ]
        }
      ]
    },
    {
      "page": 51,
      "rows": [
        {
          "id": 100,
          "top": 25,
          "height": 220,
          "blocks": [
            { "id": 2234, "width": 47, "left": 37 },
            { "id": 2235, "width": 28, "left": 0 },
            { "id": 2236, "width": 27, "left": 0 },
            { "id": 2237, "width": 27, "left": 0 },
            { "id": 2238, "width": 27, "left": 0 },
            { "id": 2239, "width": 28, "left": 0 },
            { "id": 2240, "width": 26, "left": 0 },
            { "id": 2241, "width": 28, "left": 0 },
            { "id": 2242, "width": 17, "left": 0 },
            { "id": 2243, "width": 28, "left": 0 },
            { "id": 2244, "width": 28, "left": 0 },
            { "id": 2245, "width": 23, "left": 0 },
            { "id": 2246, "width": 18, "left": 0 },
            { "id": 2247, "width": 17, "left": 0 },
            { "id": 2248, "width": 16, "left": 0 },
            { "id": 2249, "width": 17, "left": 0 },
            { "id": 2250, "width": 28, "left": 0 }
          ]
        },
        {
          "id": 101,
          "top": 266,
          "height": 212,
          "blocks": [
            { "id": 2251, "width": 49, "left": 37 },
            { "id": 2252, "width": 31, "left": 0 },
            { "id": 2253, "width": 24, "left": 0 },
            { "id": 2254, "width": 16, "left": 0 },
            { "id": 2255, "width": 18, "left": 0 },
            { "id": 2256, "width": 17, "left": 0 },
            { "id": 2257, "width": 18, "left": 0 },
            { "id": 2258, "width": 32, "left": 0 },
            { "id": 2259, "width": 34, "left": 0 },
            { "id": 2260, "width": 33, "left": 0 },
            { "id": 2261, "width": 28, "left": 0 },
            { "id": 2262, "width": 33, "left": 0 },
            { "id": 2263, "width": 34, "left": 0 },
            { "id": 2264, "width": 33, "left": 0 },
            { "id": 2265, "width": 30, "left": 0 }
          ]
        }
      ]
    },
    {
      "page": 52,
      "rows": [
        {
          "id": 102,
          "top": 30,
          "height": 211,
          "blocks": [
            { "id": 3001, "width": 53, "left": 99 },
            { "id": 3002, "width": 26, "left": 0 },
            { "id": 3003, "width": 48, "left": 0 },
            { "id": 3004, "width": 50, "left": 0 },
            { "id": 3005, "width": 46, "left": 0 },
            { "id": 3006, "width": 46, "left": 0 },
            { "id": 3007, "width": 50, "left": 0 },
            { "id": 3008, "width": 53, "left": 0 }
          ]
        },
        {
          "id": 103,
          "top": 256,
          "height": 218,
          "blocks": [
            { "id": 3009, "width": 46, "left": 34 },
            { "id": 3010, "width": 27, "left": 0 },
            { "id": 3011, "width": 25, "left": 0 },
            { "id": 3012, "width": 25, "left": 0 },
            { "id": 3013, "width": 53, "left": 0 },
            { "id": 3014, "width": 50, "left": 0 },
            { "id": 3015, "width": 52, "left": 0 },
            { "id": 3016, "width": 51, "left": 0 },
            { "id": 3017, "width": 55, "left": 0 },
            { "id": 3018, "width": 50, "left": 0 }
          ]
        }
      ]
    },
    {
      "page": 53,
      "rows": [
        {
          "id": 104,
          "top": 18,
          "height": 224,
          "blocks": [
            { "id": 3019, "width": 92, "left": 40 },
            { "id": 3020, "width": 71, "left": 0 },
            { "id": 3021, "width": 89, "left": 0 },
            { "id": 3022, "width": 88, "left": 0 },
            { "id": 3023, "width": 89, "left": 0 }
          ]
        },
        {
          "id": 105,
          "top": 256,
          "height": 220,
          "blocks": [
            { "id": 3024, "width": 123, "left": 37 },
            { "id": 3025, "width": 103, "left": 0 },
            { "id": 3026, "width": 102, "left": 0 },
            { "id": 3027, "width": 104, "left": 0 }
          ]
        }
      ]
    },
    {
      "page": 54,
      "rows": [
        {
          "id": 106,
          "top": 15,
          "height": 220,
          "blocks": [
            { "id": 3028, "width": 123, "left": 37 },
            { "id": 3029, "width": 104, "left": 0 },
            { "id": 3030, "width": 102, "left": 0 },
            { "id": 3031, "width": 103, "left": 0 }
          ]
        },
        {
          "id": 107,
          "top": 246,
          "height": 232,
          "blocks": [
            { "id": 3032, "width": 137, "left": 34 },
            { "id": 3033, "width": 62, "left": 0 },
            { "id": 3034, "width": 70, "left": 0 },
            { "id": 3035, "width": 48, "left": 0 },
            { "id": 3036, "width": 66, "left": 0 },
            { "id": 3037, "width": 52, "left": 0 }
          ]
        }
      ]
    },
    {
      "page": 55,
      "rows": [
        {
          "id": 108,
          "top": 16,
          "height": 225,
          "blocks": [
            { "id": 3038, "width": 75, "left": 39 },
            { "id": 3039, "width": 40, "left": 0 },
            { "id": 3040, "width": 57, "left": 0 },
            { "id": 3041, "width": 89, "left": 0 },
            { "id": 3042, "width": 88, "left": 0 },
            { "id": 3043, "width": 51, "left": 0 },
            { "id": 3044, "width": 29, "left": 0 }
          ]
        },
        {
          "id": 109,
          "top": 253,
          "height": 221,
          "blocks": [
            { "id": 3045, "width": 103, "left": 37 },
            { "id": 3046, "width": 83, "left": 0 },
            { "id": 3047, "width": 52, "left": 0 },
            { "id": 3048, "width": 30, "left": 0 },
            { "id": 3049, "width": 81, "left": 0 },
            { "id": 3050, "width": 82, "left": 0 }
          ]
        }
      ]
    },
    {
      "page": 56,
      "rows": [
        {
          "id": 110,
          "top": 17,
          "height": 228,
          "blocks": [
            { "id": 3051, "width": 71, "left": 37 },
            { "id": 3052, "width": 48, "left": 0 },
            { "id": 3053, "width": 45, "left": 0 },
            { "id": 3054, "width": 52, "left": 0 },
            { "id": 3055, "width": 68, "left": 0 },
            { "id": 3056, "width": 81, "left": 0 },
            { "id": 3057, "width": 70, "left": 0 }
          ]
        },
        {
          "id": 111,
          "top": 257,
          "height": 222,
          "blocks": [
            { "id": 3058, "width": 85, "left": 34 },
            { "id": 3059, "width": 63, "left": 0 },
            { "id": 3060, "width": 64, "left": 0 },
            { "id": 3061, "width": 64, "left": 0 },
            { "id": 3062, "width": 30, "left": 0 },
            { "id": 3063, "width": 28, "left": 0 },
            { "id": 3064, "width": 102, "left": 0 }
          ]
        }
      ]
    },
    {
      "page": 57,
      "rows": [
        {
          "id": 112,
          "top": 17,
          "height": 221,
          "blocks": [
            { "id": 3065, "width": 108, "left": 38 },
            { "id": 3066, "width": 63, "left": 0 },
            { "id": 3067, "width": 64, "left": 0 },
            { "id": 3068, "width": 98, "left": 0 },
            { "id": 3069, "width": 97, "left": 0 }
          ]
        },
        {
          "id": 113,
          "top": 251,
          "height": 224,
          "blocks": [
            { "id": 3070, "width": 78, "left": 37 },
            { "id": 3071, "width": 60, "left": 0 },
            { "id": 3072, "width": 100, "left": 0 },
            { "id": 3073, "width": 98, "left": 0 },
            { "id": 3074, "width": 95, "left": 0 }
          ]
        }
      ]
    },
    {
      "page": 58,
      "rows": [
        {
          "id": 114,
          "top": 15,
          "height": 217,
          "blocks": [
            { "id": 3075, "width": 118, "left": 39 },
            { "id": 3076, "width": 106, "left": 0 },
            { "id": 3077, "width": 112, "left": 0 },
            { "id": 3078, "width": 96, "left": 0 }
          ]
        },
        {
          "id": 115,
          "top": 246,
          "height": 232,
          "blocks": [
            { "id": 3079, "width": 104, "left": 36 },
            { "id": 3080, "width": 83, "left": 0 },
            { "id": 3081, "width": 81, "left": 0 },
            { "id": 3082, "width": 81, "left": 0 },
            { "id": 3083, "width": 85, "left": 0 }
          ]
        }
      ]
    },
    {
      "page": 59,
      "rows": [
        {
          "id": 116,
          "top": 18,
          "height": 221,
          "blocks": [
            { "id": 3084, "width": 105, "left": 40 },
            { "id": 3085, "width": 81, "left": 0 },
            { "id": 3086, "width": 81, "left": 0 },
            { "id": 3087, "width": 80, "left": 0 },
            { "id": 3088, "width": 80, "left": 0 }
          ]
        },
        {
          "id": 117,
          "top": 256,
          "height": 223,
          "blocks": [
            { "id": 3089, "width": 62, "left": 38 },
            { "id": 3090, "width": 53, "left": 0 },
            { "id": 3091, "width": 41, "left": 0 },
            { "id": 3092, "width": 54, "left": 0 },
            { "id": 3093, "width": 41, "left": 0 },
            { "id": 3094, "width": 59, "left": 0 },
            { "id": 3095, "width": 55, "left": 0 },
            { "id": 3096, "width": 65, "left": 0 }
          ]
        }
      ]
    },
    {
      "page": 60,
      "rows": [
        {
          "id": 118,
          "top": 18,
          "height": 205,
          "blocks": [
            { "id": 3097, "width": 75, "left": 38 },
            { "id": 3098, "width": 51, "left": 0 },
            { "id": 3099, "width": 51, "left": 0 },
            { "id": 3100, "width": 51, "left": 0 },
            { "id": 3101, "width": 54, "left": 0 },
            { "id": 3102, "width": 53, "left": 0 },
            { "id": 3103, "width": 48, "left": 0 },
            { "id": 3104, "width": 50, "left": 0 }
          ]
        },
        {
          "id": 119,
          "top": 238,
          "height": 230,
          "blocks": [
            { "id": 3105, "width": 70, "left": 36 },
            { "id": 3106, "width": 120, "left": 0 },
            { "id": 3107, "width": 120, "left": 0 },
            { "id": 3108, "width": 121, "left": 0 }
          ]
        }
      ]
    },
    {
      "page": 61,
      "rows": [
        {
          "id": 120,
          "top": 19,
          "height": 213,
          "blocks": [
            { "id": 3109, "width": 119, "left": 41 },
            { "id": 3110, "width": 98, "left": 0 },
            { "id": 3111, "width": 83, "left": 0 },
            { "id": 3112, "width": 23, "left": 0 },
            { "id": 3113, "width": 75, "left": 0 },
            { "id": 3114, "width": 28, "left": 0 }
          ]
        },
        {
          "id": 121,
          "top": 254,
          "height": 221,
          "blocks": [
            { "id": 3115, "width": 107, "left": 39 },
            { "id": 3116, "width": 28, "left": 0 },
            { "id": 3117, "width": 85, "left": 0 },
            { "id": 3118, "width": 30, "left": 0 },
            { "id": 3119, "width": 88, "left": 0 },
            { "id": 3120, "width": 90, "left": 0 }
          ]
        }
      ]
    },
    {
      "page": 62,
      "rows": [
        {
          "id": 122,
          "top": 17,
          "height": 225,
          "blocks": [
            { "id": 3121, "width": 98, "left": 38 },
            { "id": 3122, "width": 82, "left": 0 },
            { "id": 3123, "width": 83, "left": 0 },
            { "id": 3124, "width": 57, "left": 0 },
            { "id": 3125, "width": 57, "left": 0 },
            { "id": 3126, "width": 53, "left": 0 }
          ]
        },
        {
          "id": 123,
          "top": 255,
          "height": 221,
          "blocks": [
            { "id": 3127, "width": 74, "left": 35 },
            { "id": 3128, "width": 55, "left": 0 },
            { "id": 3129, "width": 53, "left": 0 },
            { "id": 3130, "width": 39, "left": 0 },
            { "id": 3131, "width": 40, "left": 0 },
            { "id": 3132, "width": 43, "left": 0 },
            { "id": 3133, "width": 43, "left": 0 },
            { "id": 3134, "width": 42, "left": 0 },
            { "id": 3135, "width": 45, "left": 0 }
          ]
        }
      ]
    },
    {
      "page": 63,
      "rows": [
        {
          "id": 124,
          "top": 17,
          "height": 216,
          "blocks": [
            { "id": 3136, "width": 49, "left": 40 },
            { "id": 3137, "width": 34, "left": 0 },
            { "id": 3138, "width": 26, "left": 0 },
            { "id": 3139, "width": 35, "left": 0 },
            { "id": 3140, "width": 46, "left": 0 },
            { "id": 3141, "width": 35, "left": 0 },
            { "id": 3142, "width": 27, "left": 0 },
            { "id": 3143, "width": 34, "left": 0 },
            { "id": 3144, "width": 71, "left": 0 },
            { "id": 3145, "width": 70, "left": 0 }
          ]
        },
        {
          "id": 125,
          "top": 249,
          "height": 225,
          "blocks": [
            { "id": 3146, "width": 47, "left": 38 },
            { "id": 3147, "width": 23, "left": 0 },
            { "id": 3148, "width": 24, "left": 0 },
            { "id": 3149, "width": 73, "left": 0 },
            { "id": 3150, "width": 56, "left": 0 },
            { "id": 3151, "width": 28, "left": 0 },
            { "id": 3152, "width": 24, "left": 0 },
            { "id": 3153, "width": 44, "left": 0 },
            { "id": 3154, "width": 49, "left": 0 },
            { "id": 3155, "width": 49, "left": 0 }
          ]
        }
      ]
    },
    {
      "page": 64,
      "rows": [
        {
          "id": 126,
          "top": 44,
          "height": 209,
          "blocks": [
            { "id": 4001, "width": 63, "left": 98 },
            { "id": 4002, "width": 29, "left": 0 },
            { "id": 4003, "width": 36, "left": 0 },
            { "id": 4004, "width": 37, "left": 0 },
            { "id": 4005, "width": 31, "left": 0 },
            { "id": 4006, "width": 29, "left": 0 },
            { "id": 4007, "width": 36, "left": 0 },
            { "id": 4008, "width": 37, "left": 0 },
            { "id": 4009, "width": 41, "left": 0 },
            { "id": 4010, "width": 31, "left": 0 }
          ]
        },
        {
          "id": 127,
          "top": 266,
          "height": 209,
          "blocks": [
            { "id": 4011, "width": 55, "left": 35 },
            { "id": 4012, "width": 36, "left": 0 },
            { "id": 4013, "width": 38, "left": 0 },
            { "id": 4014, "width": 36, "left": 0 },
            { "id": 4015, "width": 37, "left": 0 },
            { "id": 4016, "width": 40, "left": 0 },
            { "id": 4017, "width": 64, "left": 0 },
            { "id": 4018, "width": 63, "left": 0 },
            { "id": 4019, "width": 64, "left": 0 }
          ]
        }
      ]
    },
    {
      "page": 65,
      "rows": [
        {
          "id": 128,
          "top": 22,
          "height": 214,
          "blocks": [
            { "id": 4020, "width": 85, "left": 40 },
            { "id": 4021, "width": 64, "left": 0 },
            { "id": 4022, "width": 64, "left": 0 },
            { "id": 4023, "width": 64, "left": 0 },
            { "id": 4024, "width": 62, "left": 0 },
            { "id": 4025, "width": 89, "left": 0 }
          ]
        },
        {
          "id": 129,
          "top": 253,
          "height": 222,
          "blocks": [
            { "id": 4026, "width": 124, "left": 37 },
            { "id": 4027, "width": 102, "left": 0 },
            { "id": 4028, "width": 102, "left": 0 },
            { "id": 4029, "width": 101, "left": 0 }
          ]
        }
      ]
    },
    {
      "page": 66,
      "rows": [
        {
          "id": 130,
          "top": 24,
          "height": 215,
          "blocks": [
            { "id": 4030, "width": 119, "left": 37 },
            { "id": 4031, "width": 98, "left": 0 },
            { "id": 4032, "width": 73, "left": 0 },
            { "id": 4033, "width": 72, "left": 0 },
            { "id": 4034, "width": 71, "left": 0 }
          ]
        },
        {
          "id": 131,
          "top": 254,
          "height": 221,
          "blocks": [
            { "id": 4035, "width": 89, "left": 33 },
            { "id": 4036, "width": 68, "left": 0 },
            { "id": 4037, "width": 69, "left": 0 },
            { "id": 4038, "width": 68, "left": 0 },
            { "id": 4039, "width": 69, "left": 0 },
            { "id": 4040, "width": 73, "left": 0 }
          ]
        }
      ]
    },
    {
      "page": 67,
      "rows": [
        {
          "id": 132,
          "top": 23,
          "height": 206,
          "blocks": [
            { "id": 4041, "width": 92, "left": 39 },
            { "id": 4042, "width": 59, "left": 0 },
            { "id": 4043, "width": 63, "left": 0 },
            { "id": 4044, "width": 70, "left": 0 },
            { "id": 4045, "width": 69, "left": 0 },
            { "id": 4046, "width": 75, "left": 0 }
          ]
        },
        {
          "id": 133,
          "top": 247,
          "height": 227,
          "blocks": [
            { "id": 4047, "width": 100, "left": 37 },
            { "id": 4048, "width": 86, "left": 0 },
            { "id": 4049, "width": 85, "left": 0 },
            { "id": 4050, "width": 76, "left": 0 },
            { "id": 4051, "width": 82, "left": 0 }
          ]
        }
      ]
    },
    {
      "page": 68,
      "rows": [
        {
          "id": 134,
          "top": 26,
          "height": 223,
          "blocks": [
            { "id": 4052, "width": 88, "left": 37 },
            { "id": 4053, "width": 75, "left": 0 },
            { "id": 4054, "width": 40, "left": 0 },
            { "id": 4055, "width": 40, "left": 0 },
            { "id": 4056, "width": 49, "left": 0 },
            { "id": 4057, "width": 46, "left": 0 },
            { "id": 4058, "width": 47, "left": 0 },
            { "id": 4059, "width": 47, "left": 0 }
          ]
        },
        {
          "id": 135,
          "top": 263,
          "height": 218,
          "blocks": [
            { "id": 4060, "width": 67, "left": 34 },
            { "id": 4061, "width": 44, "left": 0 },
            { "id": 4062, "width": 44, "left": 0 },
            { "id": 4063, "width": 74, "left": 0 },
            { "id": 4064, "width": 52, "left": 0 },
            { "id": 4065, "width": 51, "left": 0 },
            { "id": 4066, "width": 52, "left": 0 },
            { "id": 4067, "width": 51, "left": 0 }
          ]
        }
      ]
    },
    {
      "page": 69,
      "rows": [
        {
          "id": 136,
          "top": 19,
          "height": 208,
          "blocks": [
            { "id": 4068, "width": 73, "left": 40 },
            { "id": 4069, "width": 51, "left": 0 },
            { "id": 4070, "width": 53, "left": 0 },
            { "id": 4071, "width": 53, "left": 0 },
            { "id": 4072, "width": 65, "left": 0 },
            { "id": 4073, "width": 65, "left": 0 },
            { "id": 4074, "width": 67, "left": 0 }
          ]
        },
        {
          "id": 137,
          "top": 243,
          "height": 229,
          "blocks": [
            { "id": 4075, "width": 89, "left": 38 },
            { "id": 4076, "width": 69, "left": 0 },
            { "id": 4077, "width": 74, "left": 0 },
            { "id": 4078, "width": 98, "left": 0 },
            { "id": 4079, "width": 99, "left": 0 }
          ]
        }
      ]
    },
    {
      "page": 70,
      "rows": [
        {
          "id": 138,
          "top": 22,
          "height": 210,
          "blocks": [
            { "id": 4080, "width": 87, "left": 37 },
            { "id": 4081, "width": 66, "left": 0 },
            { "id": 4082, "width": 66, "left": 0 },
            { "id": 4083, "width": 72, "left": 0 },
            { "id": 4084, "width": 75, "left": 0 },
            { "id": 4085, "width": 65, "left": 0 }
          ]
        },
        {
          "id": 139,
          "top": 250,
          "height": 224,
          "blocks": [
            { "id": 4086, "width": 92, "left": 33 },
            { "id": 4087, "width": 69, "left": 0 },
            { "id": 4088, "width": 65, "left": 0 },
            { "id": 4089, "width": 68, "left": 0 },
            { "id": 4090, "width": 70, "left": 0 },
            { "id": 4091, "width": 70, "left": 0 }
          ]
        }
      ]
    },
    {
      "page": 71,
      "rows": [
        {
          "id": 140,
          "top": 24,
          "height": 223,
          "blocks": [
            { "id": 4092, "width": 84, "left": 41 },
            { "id": 4093, "width": 76, "left": 0 },
            { "id": 4094, "width": 70, "left": 0 },
            { "id": 4095, "width": 45, "left": 0 },
            { "id": 4096, "width": 39, "left": 0 },
            { "id": 4097, "width": 43, "left": 0 },
            { "id": 4098, "width": 69, "left": 0 }
          ]
        },
        {
          "id": 141,
          "top": 263,
          "height": 211,
          "blocks": [
            { "id": 4099, "width": 104, "left": 38 },
            { "id": 4100, "width": 80, "left": 0 },
            { "id": 4101, "width": 79, "left": 0 },
            { "id": 4102, "width": 84, "left": 0 },
            { "id": 4103, "width": 81, "left": 0 }
          ]
        }
      ]
    },
    {
      "page": 72,
      "rows": [
        {
          "id": 142,
          "top": 23,
          "height": 213,
          "blocks": [
            { "id": 4104, "width": 98, "left": 37 },
            { "id": 4105, "width": 81, "left": 0 },
            { "id": 4106, "width": 84, "left": 0 },
            { "id": 4107, "width": 85, "left": 0 },
            { "id": 4108, "width": 84, "left": 0 }
          ]
        },
        {
          "id": 143,
          "top": 259,
          "height": 214,
          "blocks": [
            { "id": 4109, "width": 94, "left": 35 },
            { "id": 4110, "width": 72, "left": 0 },
            { "id": 4111, "width": 67, "left": 0 },
            { "id": 4112, "width": 66, "left": 0 },
            { "id": 4113, "width": 66, "left": 0 },
            { "id": 4114, "width": 69, "left": 0 }
          ]
        }
      ]
    },
    {
      "page": 73,
      "rows": [
        {
          "id": 144,
          "top": 22,
          "height": 226,
          "blocks": [
            { "id": 4115, "width": 89, "left": 40 },
            { "id": 4116, "width": 66, "left": 0 },
            { "id": 4117, "width": 67, "left": 0 },
            { "id": 4118, "width": 65, "left": 0 },
            { "id": 4119, "width": 70, "left": 0 },
            { "id": 4120, "width": 69, "left": 0 }
          ]
        },
        {
          "id": 145,
          "top": 263,
          "height": 212,
          "blocks": [
            { "id": 4121, "width": 99, "left": 36 },
            { "id": 4122, "width": 65, "left": 0 },
            { "id": 4123, "width": 66, "left": 0 },
            { "id": 4124, "width": 66, "left": 0 },
            { "id": 4125, "width": 66, "left": 0 },
            { "id": 4126, "width": 68, "left": 0 }
          ]
        }
      ]
    },
    {
      "page": 74,
      "rows": [
        {
          "id": 146,
          "top": 20,
          "height": 208,
          "blocks": [
            { "id": 4127, "width": 86, "left": 38 },
            { "id": 4128, "width": 63, "left": 0 },
            { "id": 4129, "width": 71, "left": 0 },
            { "id": 4130, "width": 60, "left": 0 },
            { "id": 4131, "width": 61, "left": 0 },
            { "id": 4132, "width": 92, "left": 0 }
          ]
        },
        {
          "id": 147,
          "top": 248,
          "height": 228,
          "blocks": [
            { "id": 4133, "width": 122, "left": 34 },
            { "id": 4134, "width": 101, "left": 0 },
            { "id": 4135, "width": 107, "left": 0 },
            { "id": 4136, "width": 105, "left": 0 }
          ]
        }
      ]
    },
    {
      "page": 75,
      "rows": [
        {
          "id": 148,
          "top": 25,
          "height": 228,
          "blocks": [
            { "id": 4137, "width": 130, "left": 40 },
            { "id": 4138, "width": 106, "left": 0 },
            { "id": 4139, "width": 106, "left": 0 },
            { "id": 4140, "width": 85, "left": 0 }
          ]
        },
        {
          "id": 149,
          "top": 267,
          "height": 209,
          "blocks": [
            { "id": 4141, "width": 88, "left": 37 },
            { "id": 4142, "width": 67, "left": 0 },
            { "id": 4143, "width": 68, "left": 0 },
            { "id": 4144, "width": 67, "left": 0 },
            { "id": 4145, "width": 70, "left": 0 },
            { "id": 4146, "width": 69, "left": 0 }
          ]
        }
      ]
    },
    {
      "page": 76,
      "rows": [
        {
          "id": 150,
          "top": 22,
          "height": 224,
          "blocks": [
            { "id": 4147, "width": 94, "left": 37 },
            { "id": 4148, "width": 71, "left": 0 },
            { "id": 4149, "width": 78, "left": 0 },
            { "id": 4150, "width": 64, "left": 0 },
            { "id": 4151, "width": 62, "left": 0 },
            { "id": 4152, "width": 65, "left": 0 }
          ]
        },
        {
          "id": 151,
          "top": 261,
          "height": 217,
          "blocks": [
            { "id": 4153, "width": 82, "left": 32 },
            { "id": 4154, "width": 72, "left": 0 },
            { "id": 4155, "width": 73, "left": 0 },
            { "id": 4156, "width": 73, "left": 0 },
            { "id": 4157, "width": 69, "left": 0 },
            { "id": 4158, "width": 68, "left": 0 }
          ]
        }
      ]
    },
    {
      "page": 77,
      "rows": [
        {
          "id": 152,
          "top": 25,
          "height": 233,
          "blocks": [
            { "id": 4159, "width": 83, "left": 38 },
            { "id": 4160, "width": 62, "left": 0 },
            { "id": 4161, "width": 63, "left": 0 },
            { "id": 4162, "width": 40, "left": 0 },
            { "id": 4163, "width": 39, "left": 0 },
            { "id": 4164, "width": 48, "left": 0 },
            { "id": 4165, "width": 46, "left": 0 },
            { "id": 4166, "width": 48, "left": 0 }
          ]
        },
        {
          "id": 153,
          "top": 276,
          "height": 205,
          "blocks": [
            { "id": 4167, "width": 64, "left": 36 },
            { "id": 4168, "width": 46, "left": 0 },
            { "id": 4169, "width": 65, "left": 0 },
            { "id": 4170, "width": 64, "left": 0 },
            { "id": 4171, "width": 65, "left": 0 },
            { "id": 4172, "width": 64, "left": 0 },
            { "id": 4173, "width": 63, "left": 0 }
          ]
        }
      ]
    },
    {
      "page": 78,
      "rows": [
        {
          "id": 154,
          "top": 19,
          "height": 215,
          "blocks": [
            { "id": 4174, "width": 86, "left": 36 },
            { "id": 4175, "width": 90, "left": 0 },
            { "id": 4176, "width": 89, "left": 0 },
            { "id": 4177, "width": 41, "left": 0 },
            { "id": 4178, "width": 30, "left": 0 },
            { "id": 4179, "width": 35, "left": 0 },
            { "id": 4180, "width": 28, "left": 0 },
            { "id": 4181, "width": 35, "left": 0 }
          ]
        },
        {
          "id": 155,
          "top": 253,
          "height": 222,
          "blocks": [
            { "id": 4182, "width": 61, "left": 32 },
            { "id": 4183, "width": 45, "left": 0 },
            { "id": 4184, "width": 40, "left": 0 },
            { "id": 4185, "width": 38, "left": 0 },
            { "id": 4186, "width": 41, "left": 0 },
            { "id": 4187, "width": 44, "left": 0 },
            { "id": 4188, "width": 38, "left": 0 },
            { "id": 4189, "width": 38, "left": 0 },
            { "id": 4190, "width": 91, "left": 0 }
          ]
        }
      ]
    },
    {
      "page": 79,
      "rows": [
        {
          "id": 156,
          "top": 22,
          "height": 215,
          "blocks": [
            { "id": 4191, "width": 119, "left": 39 },
            { "id": 4192, "width": 100, "left": 0 },
            { "id": 4193, "width": 100, "left": 0 },
            { "id": 4194, "width": 109, "left": 0 }
          ]
        },
        {
          "id": 157,
          "top": 254,
          "height": 228,
          "blocks": [
            { "id": 4195, "width": 113, "left": 37 },
            { "id": 4196, "width": 43, "left": 0 },
            { "id": 4197, "width": 47, "left": 0 },
            { "id": 4198, "width": 58, "left": 0 },
            { "id": 4199, "width": 56, "left": 0 },
            { "id": 4200, "width": 55, "left": 0 },
            { "id": 4201, "width": 58, "left": 0 }
          ]
        }
      ]
    },
    {
      "page": 80,
      "rows": [
        {
          "id": 158,
          "top": 21,
          "height": 224,
          "blocks": [
            { "id": 4202, "width": 83, "left": 37 },
            { "id": 4203, "width": 75, "left": 0 },
            { "id": 4204, "width": 102, "left": 0 },
            { "id": 4205, "width": 102, "left": 0 },
            { "id": 4206, "width": 73, "left": 0 }
          ]
        },
        {
          "id": 159,
          "top": 264,
          "height": 214,
          "blocks": [
            { "id": 4207, "width": 86, "left": 34 },
            { "id": 4208, "width": 69, "left": 0 },
            { "id": 4209, "width": 67, "left": 0 },
            { "id": 4210, "width": 65, "left": 0 },
            { "id": 4211, "width": 68, "left": 0 },
            { "id": 4212, "width": 81, "left": 0 }
          ]
        }
      ]
    },
    {
      "page": 81,
      "rows": [
        {
          "id": 160,
          "top": 25,
          "height": 218,
          "blocks": [
            { "id": 4213, "width": 87, "left": 40 },
            { "id": 4214, "width": 65, "left": 0 },
            { "id": 4215, "width": 67, "left": 0 },
            { "id": 4216, "width": 72, "left": 0 },
            { "id": 4217, "width": 68, "left": 0 },
            { "id": 4218, "width": 69, "left": 0 }
          ]
        },
        {
          "id": 161,
          "top": 263,
          "height": 217,
          "blocks": [
            { "id": 4219, "width": 120, "left": 38 },
            { "id": 4220, "width": 103, "left": 0 },
            { "id": 4221, "width": 102, "left": 0 },
            { "id": 4222, "width": 105, "left": 0 }
          ]
        }
      ]
    },
    {
      "page": 82,
      "rows": [
        {
          "id": 162,
          "top": 24,
          "height": 219,
          "blocks": [
            { "id": 4223, "width": 124, "left": 37 },
            { "id": 4224, "width": 102, "left": 0 },
            { "id": 4225, "width": 103, "left": 0 },
            { "id": 4226, "width": 105, "left": 0 }
          ]
        },
        {
          "id": 163,
          "top": 263,
          "height": 217,
          "blocks": [
            { "id": 4227, "width": 124, "left": 34 },
            { "id": 4228, "width": 103, "left": 0 },
            { "id": 4229, "width": 103, "left": 0 },
            { "id": 4230, "width": 104, "left": 0 }
          ]
        }
      ]
    },
    {
      "page": 83,
      "rows": [
        {
          "id": 164,
          "top": 26,
          "height": 215,
          "blocks": [
            { "id": 4231, "width": 123, "left": 39 },
            { "id": 4232, "width": 101, "left": 0 },
            { "id": 4233, "width": 101, "left": 0 },
            { "id": 4234, "width": 103, "left": 0 }
          ]
        },
        {
          "id": 165,
          "top": 260,
          "height": 214,
          "blocks": [
            { "id": 4235, "width": 108, "left": 36 },
            { "id": 4236, "width": 86, "left": 0 },
            { "id": 4237, "width": 38, "left": 0 },
            { "id": 4238, "width": 17, "left": 0 },
            { "id": 4239, "width": 30, "left": 0 },
            { "id": 4240, "width": 17, "left": 0 },
            { "id": 4241, "width": 30, "left": 0 },
            { "id": 4242, "width": 29, "left": 0 },
            { "id": 4243, "width": 38, "left": 0 },
            { "id": 4244, "width": 36, "left": 0 }
          ]
        }
      ]
    },
    {
      "page": 84,
      "rows": [
        {
          "id": 166,
          "top": 22,
          "height": 218,
          "blocks": [
            { "id": 4245, "width": 58, "left": 35 },
            { "id": 4246, "width": 33, "left": 0 },
            { "id": 4247, "width": 42, "left": 0 },
            { "id": 4248, "width": 35, "left": 0 },
            { "id": 4249, "width": 32, "left": 0 },
            { "id": 4250, "width": 35, "left": 0 },
            { "id": 4251, "width": 31, "left": 0 },
            { "id": 4252, "width": 35, "left": 0 },
            { "id": 4253, "width": 31, "left": 0 },
            { "id": 4254, "width": 33, "left": 0 },
            { "id": 4255, "width": 35, "left": 0 },
            { "id": 4256, "width": 34, "left": 0 }
          ]
        },
        {
          "id": 167,
          "top": 258,
          "height": 217,
          "blocks": [
            { "id": 4257, "width": 57, "left": 34 },
            { "id": 4258, "width": 39, "left": 0 },
            { "id": 4259, "width": 20, "left": 0 },
            { "id": 4260, "width": 69, "left": 0 },
            { "id": 4261, "width": 70, "left": 0 },
            { "id": 4262, "width": 69, "left": 0 },
            { "id": 4263, "width": 69, "left": 0 },
            { "id": 4264, "width": 40, "left": 0 }
          ]
        }
      ]
    }
  ]
}
